// converted by version 1.3
// on Sat Jan 03 00:16:02 ICT 2026

.package ParkCard {
	.aid 0x11:0x11:0x11:0x11:0x11;
	.version 1.0;

	.imports {
		0xA0:0x0:0x0:0x0:0x62:0x0:0x1 1.0;		//java/lang
		0xA0:0x0:0x0:0x0:0x62:0x1:0x2 1.2;		//javacard/security
		0xA0:0x0:0x0:0x0:0x62:0x1:0x1 1.2;		//javacard/framework
		0xA0:0x0:0x0:0x0:0x62:0x2:0x1 1.2;		//javacardx/crypto
	}

	.applet {
		0x11:0x11:0x11:0x11:0x11:0x0 CustomerCardApplet;
	}

	.constantPool {
		// 0
		instanceFieldRef byte[] CardModel/customerID;
		// 1
		instanceFieldRef 1.16 CardModel/rsaKeyPair;
		// 2
		instanceFieldRef 1.8 CardModel/privateKey;
		// 3
		instanceFieldRef 1.9 CardModel/publicKey;
		// 4
		instanceFieldRef byte[] CardModel/name;
		// 5
		instanceFieldRef byte[] CardModel/dateOfBirth;
		// 6
		instanceFieldRef byte[] CardModel/phoneNumber;
		// 7
		instanceFieldRef byte[] CardModel/balance;
		// 8
		instanceFieldRef byte[] CardModel/customerPhoto;
		// 9
		instanceFieldRef byte[] CardModel/decryptedPhoto;
		// 10
		instanceFieldRef short CardModel/photoLength;
		// 11
		instanceFieldRef short CardModel/photoWriteOffset;
		// 12
		instanceFieldRef short CardModel/actualPhotoLength;
		// 13
		instanceFieldRef short CardModel/encryptedPhotoLength;
		// 14
		instanceFieldRef byte[] CardModel/gameList;
		// 15
		instanceFieldRef short[] CardModel/gameCountRef;
		// 16
		instanceFieldRef byte[] CardModel/iv;
		// 17
		instanceFieldRef byte[] CardModel/salt;
		// 18
		instanceFieldRef boolean CardModel/dataReady;
		// 19
		instanceFieldRef boolean CardModel/dataEncrypted;
		// 20
		instanceFieldRef boolean CardModel/rsaKeyReady;
		// 21
		instanceFieldRef byte[] CardModel/wrappedMasterKey;
		// 22
		instanceFieldRef boolean CardModel/masterKeyWrapped;
		// 23
		instanceFieldRef byte[] CardModel/wrappedMasterKeyAdmin;
		// 24
		instanceFieldRef boolean CardModel/masterKeyWrappedAdmin;
		// 25
		instanceFieldRef byte[] CardModel/tempDecryptBuffer;
		// 26
		instanceFieldRef 3.1 CryptoManager/cbcCipher;
		// 27
		instanceFieldRef 3.1 CryptoManager/ecbCipher;
		// 28
		instanceFieldRef byte[] CryptoManager/aesKey;
		// 29
		instanceFieldRef byte[] CryptoManager/pinKey;
		// 30
		instanceFieldRef byte[] CryptoManager/derivedBuf;
		// 31
		instanceFieldRef boolean CryptoManager/keyReady;
		// 32
		instanceFieldRef PBKDF2 CryptoManager/pbkdf2;
		// 33
		instanceFieldRef CardModel CustomerCardApplet/model;
		// 34
		instanceFieldRef PinManager CustomerCardApplet/pinMgr;
		// 35
		instanceFieldRef GameManager CustomerCardApplet/gameMgr;
		// 36
		instanceFieldRef CryptoManager CustomerCardApplet/cryptoMgr;
		// 37
		instanceFieldRef byte[] GameManager/gameList;
		// 38
		instanceFieldRef short[] GameManager/gameCountRef;
		// 39
		instanceFieldRef 1.11 PBKDF2/sha1;
		// 40
		instanceFieldRef byte[] PBKDF2/ipad;
		// 41
		instanceFieldRef byte[] PBKDF2/opad;
		// 42
		instanceFieldRef byte[] PBKDF2/innerHash;
		// 43
		instanceFieldRef 2.9 PinManager/userPIN;
		// 44
		instanceFieldRef 2.9 PinManager/adminPIN;
		// 45
		instanceFieldRef 2.9 PinManager/pukPIN;
		// 46
		instanceFieldRef boolean PinManager/pinCreated;
		// 47
		instanceFieldRef boolean PinManager/adminPinCreated;
		// 48
		instanceFieldRef CryptoManager PinManager/cryptoManager;
		// 49
		instanceFieldRef CardModel PinManager/cardModel;
		// 50
		virtualMethodRef CryptoManager/decrypt([BSS[BS[BS)V;
		// 51
		virtualMethodRef 2.10.7()S;		// javacard/framework/APDU.setOutgoing()S
		// 52
		virtualMethodRef 2.10.9(S)V;		// javacard/framework/APDU.setOutgoingLength(S)V
		// 53
		virtualMethodRef 2.10.5([BSS)V;		// javacard/framework/APDU.sendBytesLong([BSS)V
		// 54
		virtualMethodRef CryptoManager/encryptPhotoECB([BSS[BS)V;
		// 55
		virtualMethodRef CryptoManager/decryptPhotoECB([BSS[BS)V;
		// 56
		virtualMethodRef 2.10.4(SS)V;		// javacard/framework/APDU.sendBytes(SS)V
		// 57
		staticMethodRef 3.1.0(BZ)Ljavacardx/crypto/Cipher;;		// javacardx/crypto/Cipher.getInstance(BZ)Ljavacardx/crypto/Cipher;
			.descriptor	Ljavacardx/crypto/Cipher;	3.1;

		// 58
		staticMethodRef 0.0.0()V;		// java/lang/Object.<init>()V
		// 59
		virtualMethodRef 1.16.2()Ljavacard/security/PrivateKey;;		// javacard/security/KeyPair.getPrivate()Ljavacard/security/PrivateKey;
			.descriptor	Ljavacard/security/PrivateKey;	1.2;

		// 60
		classRef 1.8;		// javacard/security/RSAPrivateKey
		// 61
		classRef 1.16;		// javacard/security/KeyPair
		// 62
		virtualMethodRef 1.16.3()Ljavacard/security/PublicKey;;		// javacard/security/KeyPair.getPublic()Ljavacard/security/PublicKey;
			.descriptor	Ljavacard/security/PublicKey;	1.3;

		// 63
		classRef 1.9;		// javacard/security/RSAPublicKey
		// 64
		classRef PBKDF2;
		// 65
		staticMethodRef PBKDF2/<init>()V;
		// 66
		staticMethodRef 1.16.0(BS)V;		// javacard/security/KeyPair.<init>(BS)V
		// 67
		virtualMethodRef PBKDF2/deriveKey([BSS[BSSS[BS)V;
		// 68
		virtualMethodRef CryptoManager/deriveKeyFromPIN([BSB[BSSZ)V;
		// 69
		staticMethodRef 1.13.0(BSZ)Ljavacard/security/Key;;		// javacard/security/KeyBuilder.buildKey(BSZ)Ljavacard/security/Key;
			.descriptor	Ljavacard/security/Key;	1.0;

		// 70
		classRef 1.20;		// javacard/security/AESKey
		// 71
		virtualMethodRef 3.1.4(Ljavacard/security/Key;B[BSS)V;		// javacardx/crypto/Cipher.init(Ljavacard/security/Key;B[BSS)V
			.descriptor	Ljavacard/security/Key;	1.0;

		// 72
		virtualMethodRef 3.1.1([BSS[BS)S;		// javacardx/crypto/Cipher.doFinal([BSS[BS)S
		// 73
		virtualMethodRef 3.1.3(Ljavacard/security/Key;B)V;		// javacardx/crypto/Cipher.init(Ljavacard/security/Key;B)V
			.descriptor	Ljavacard/security/Key;	1.0;

		// 74
		staticMethodRef 2.3.0()V;		// javacard/framework/Applet.<init>()V
		// 75
		classRef CardModel;
		// 76
		staticMethodRef CardModel/<init>()V;
		// 77
		staticMethodRef 2.8.13(SB)[B;		// javacard/framework/JCSystem.makeTransientByteArray(SB)[B
		// 78
		classRef PinManager;
		// 79
		staticMethodRef PinManager/<init>()V;
		// 80
		staticMethodRef CardModel/generateIVAndSalt()V;
		// 81
		classRef GameManager;
		// 82
		staticMethodRef GameManager/<init>([B[S)V;
		// 83
		staticMethodRef 1.14.0(B)Ljavacard/security/RandomData;;		// javacard/security/RandomData.getInstance(B)Ljavacard/security/RandomData;
			.descriptor	Ljavacard/security/RandomData;	1.14;

		// 84
		classRef CryptoManager;
		// 85
		staticMethodRef CryptoManager/<init>()V;
		// 86
		virtualMethodRef 1.14.1([BSS)V;		// javacard/security/RandomData.generateData([BSS)V
		// 87
		virtualMethodRef PinManager/setCryptoManager(LParkCard/CryptoManager;)V;
		// 88
		virtualMethodRef PinManager/setCardModel(LParkCard/CardModel;)V;
		// 89
		classRef CustomerCardApplet;
		// 90
		staticMethodRef CustomerCardApplet/<init>()V;
		// 91
		virtualMethodRef 2.3.2([BSB)V;		// javacard/framework/Applet.register([BSB)V
		// 92
		virtualMethodRef 2.3.3()Z;		// javacard/framework/Applet.selectingApplet()Z
		// 93
		virtualMethodRef PinManager/createPIN(Ljavacard/framework/APDU;)V;
			.descriptor	Ljavacard/framework/APDU;	2.10;

		// 94
		staticMethodRef CustomerCardApplet/verifyPIN(Ljavacard/framework/APDU;)V;
			.descriptor	Ljavacard/framework/APDU;	2.10;

		// 95
		staticMethodRef CustomerCardApplet/changePIN(Ljavacard/framework/APDU;)V;
			.descriptor	Ljavacard/framework/APDU;	2.10;

		// 96
		virtualMethodRef PinManager/getPinTries(Ljavacard/framework/APDU;)V;
			.descriptor	Ljavacard/framework/APDU;	2.10;

		// 97
		virtualMethodRef PinManager/resetPinCounter(Ljavacard/framework/APDU;)V;
			.descriptor	Ljavacard/framework/APDU;	2.10;

		// 98
		staticMethodRef CustomerCardApplet/resetWithPUK(Ljavacard/framework/APDU;)V;
			.descriptor	Ljavacard/framework/APDU;	2.10;

		// 99
		staticMethodRef CustomerCardApplet/getCryptoInfo(Ljavacard/framework/APDU;)V;
			.descriptor	Ljavacard/framework/APDU;	2.10;

		// 100
		staticMethodRef CustomerCardApplet/requireAuthenticated()V;
		// 101
		virtualMethodRef CardModel/writeCustomerInfo(Ljavacard/framework/APDU;LParkCard/CryptoManager;)V;
			.descriptor	Ljavacard/framework/APDU;	2.10;

		// 102
		virtualMethodRef CardModel/startPhotoWrite()V;
		// 103
		virtualMethodRef CardModel/writePhotoChunk(Ljavacard/framework/APDU;)V;
			.descriptor	Ljavacard/framework/APDU;	2.10;

		// 104
		virtualMethodRef CardModel/finishPhotoWrite(Ljavacard/framework/APDU;LParkCard/CryptoManager;)V;
			.descriptor	Ljavacard/framework/APDU;	2.10;

		// 105
		virtualMethodRef CardModel/readAllData(Ljavacard/framework/APDU;LParkCard/CryptoManager;)V;
			.descriptor	Ljavacard/framework/APDU;	2.10;

		// 106
		virtualMethodRef CardModel/readPhotoChunk(Ljavacard/framework/APDU;LParkCard/CryptoManager;)V;
			.descriptor	Ljavacard/framework/APDU;	2.10;

		// 107
		virtualMethodRef CardModel/rechargeBalance(Ljavacard/framework/APDU;LParkCard/CryptoManager;)V;
			.descriptor	Ljavacard/framework/APDU;	2.10;

		// 108
		virtualMethodRef CardModel/checkBalance(Ljavacard/framework/APDU;LParkCard/CryptoManager;)V;
			.descriptor	Ljavacard/framework/APDU;	2.10;

		// 109
		virtualMethodRef CardModel/makePayment(Ljavacard/framework/APDU;LParkCard/CryptoManager;)V;
			.descriptor	Ljavacard/framework/APDU;	2.10;

		// 110
		virtualMethodRef GameManager/addOrIncreaseTickets(Ljavacard/framework/APDU;)V;
			.descriptor	Ljavacard/framework/APDU;	2.10;

		// 111
		virtualMethodRef GameManager/decreaseGameTickets(Ljavacard/framework/APDU;)V;
			.descriptor	Ljavacard/framework/APDU;	2.10;

		// 112
		virtualMethodRef GameManager/readGames(Ljavacard/framework/APDU;)V;
			.descriptor	Ljavacard/framework/APDU;	2.10;

		// 113
		virtualMethodRef GameManager/updateGameTickets(Ljavacard/framework/APDU;)V;
			.descriptor	Ljavacard/framework/APDU;	2.10;

		// 114
		virtualMethodRef GameManager/findGame(Ljavacard/framework/APDU;)V;
			.descriptor	Ljavacard/framework/APDU;	2.10;

		// 115
		virtualMethodRef GameManager/removeGame(Ljavacard/framework/APDU;)V;
			.descriptor	Ljavacard/framework/APDU;	2.10;

		// 116
		staticMethodRef CustomerCardApplet/setCustomerID(Ljavacard/framework/APDU;)V;
			.descriptor	Ljavacard/framework/APDU;	2.10;

		// 117
		staticMethodRef CustomerCardApplet/getCustomerID(Ljavacard/framework/APDU;)V;
			.descriptor	Ljavacard/framework/APDU;	2.10;

		// 118
		staticMethodRef CustomerCardApplet/setRSAExponent(Ljavacard/framework/APDU;)V;
			.descriptor	Ljavacard/framework/APDU;	2.10;

		// 119
		staticMethodRef CustomerCardApplet/setRSAModulus(Ljavacard/framework/APDU;)V;
			.descriptor	Ljavacard/framework/APDU;	2.10;

		// 120
		staticMethodRef CustomerCardApplet/signChallenge(Ljavacard/framework/APDU;)V;
			.descriptor	Ljavacard/framework/APDU;	2.10;

		// 121
		staticMethodRef CustomerCardApplet/getRSAStatus(Ljavacard/framework/APDU;)V;
			.descriptor	Ljavacard/framework/APDU;	2.10;

		// 122
		staticMethodRef CustomerCardApplet/generateRSAKeyPair(Ljavacard/framework/APDU;)V;
			.descriptor	Ljavacard/framework/APDU;	2.10;

		// 123
		staticMethodRef CustomerCardApplet/getPublicKey(Ljavacard/framework/APDU;)V;
			.descriptor	Ljavacard/framework/APDU;	2.10;

		// 124
		staticMethodRef CustomerCardApplet/verifyAdminPIN(Ljavacard/framework/APDU;)V;
			.descriptor	Ljavacard/framework/APDU;	2.10;

		// 125
		staticMethodRef CustomerCardApplet/changeAdminPIN(Ljavacard/framework/APDU;)V;
			.descriptor	Ljavacard/framework/APDU;	2.10;

		// 126
		staticMethodRef CustomerCardApplet/resetUserPIN(Ljavacard/framework/APDU;)V;
			.descriptor	Ljavacard/framework/APDU;	2.10;

		// 127
		virtualMethodRef PinManager/getAdminPinTries(Ljavacard/framework/APDU;)V;
			.descriptor	Ljavacard/framework/APDU;	2.10;

		// 128
		virtualMethodRef CardModel/isDataReady()Z;
		// 129
		virtualMethodRef PinManager/verify([BSB)Z;
		// 130
		virtualMethodRef CardModel/setDataReady(Z)V;
		// 131
		virtualMethodRef CardModel/isDataEncrypted()Z;
		// 132
		virtualMethodRef CardModel/initializeBalance(LParkCard/CryptoManager;)V;
		// 133
		virtualMethodRef CryptoManager/clearKey()V;
		// 134
		virtualMethodRef PinManager/getTriesRemaining()B;
		// 135
		virtualMethodRef PinManager/isPINValidated()Z;
		// 136
		virtualMethodRef PinManager/changePIN(Ljavacard/framework/APDU;)V;
			.descriptor	Ljavacard/framework/APDU;	2.10;

		// 137
		virtualMethodRef PinManager/resetWithPUK(Ljavacard/framework/APDU;)V;
			.descriptor	Ljavacard/framework/APDU;	2.10;

		// 138
		virtualMethodRef CardModel/getIV()[B;
		// 139
		virtualMethodRef CardModel/getSalt()[B;
		// 140
		virtualMethodRef CardModel/setCustomerID([BSS)V;
		// 141
		virtualMethodRef CardModel/getCustomerID([BS)V;
		// 142
		virtualMethodRef CardModel/setRSAExponent([BSS)V;
		// 143
		virtualMethodRef CardModel/setRSAModulus([BSS)V;
		// 144
		virtualMethodRef CardModel/isRSAKeyReady()Z;
		// 145
		virtualMethodRef CardModel/signChallenge([BSS[BS)S;
		// 146
		virtualMethodRef CardModel/generateRSAKeyPair()V;
		// 147
		virtualMethodRef CardModel/getPublicKeyModulus([BS)S;
		// 148
		virtualMethodRef CardModel/getPublicKeyExponent([BS)S;
		// 149
		virtualMethodRef PinManager/verifyAdmin([BSB)Z;
		// 150
		virtualMethodRef PinManager/getAdminTriesRemaining()B;
		// 151
		virtualMethodRef PinManager/isAdminPINValidated()Z;
		// 152
		virtualMethodRef PinManager/changeAdminPIN(Ljavacard/framework/APDU;)V;
			.descriptor	Ljavacard/framework/APDU;	2.10;

		// 153
		virtualMethodRef PinManager/resetUserPIN(Ljavacard/framework/APDU;)V;
			.descriptor	Ljavacard/framework/APDU;	2.10;

		// 154
		virtualMethodRef CryptoManager/wrapMasterKey([BS[BS[BS)V;
		// 155
		staticMethodRef 2.16.3([BSSB)S;		// javacard/framework/Util.arrayFillNonAtomic([BSSB)S
		// 156
		staticMethodRef GameManager/getGameCount()S;
		// 157
		staticMethodRef GameManager/findGameIndex(S)S;
		// 158
		staticMethodRef GameManager/setGameCount(S)V;
		// 159
		staticMethodRef 1.11.0(BZ)Ljavacard/security/MessageDigest;;		// javacard/security/MessageDigest.getInstance(BZ)Ljavacard/security/MessageDigest;
			.descriptor	Ljavacard/security/MessageDigest;	1.11;

		// 160
		virtualMethodRef CryptoManager/isKeyReady()Z;
		// 161
		virtualMethodRef CryptoManager/wrapLoadedMasterKey([BS[BS)V;
		// 162
		staticMethodRef 2.7.1(S)V;		// javacard/framework/ISOException.throwIt(S)V
		// 163
		staticMethodRef 2.16.2([BS[BSS)S;		// javacard/framework/Util.arrayCopyNonAtomic([BS[BSS)S
		// 164
		virtualMethodRef 1.11.4()V;		// javacard/security/MessageDigest.reset()V
		// 165
		virtualMethodRef 1.11.1([BSS[BS)S;		// javacard/security/MessageDigest.doFinal([BSS[BS)S
		// 166
		virtualMethodRef 1.11.5([BSS)V;		// javacard/security/MessageDigest.update([BSS)V
		// 167
		staticMethodRef PBKDF2/hmac([BSS[BSS[BS)V;
		// 168
		classRef 2.9;		// javacard/framework/OwnerPIN
		// 169
		staticMethodRef 2.9.0(BB)V;		// javacard/framework/OwnerPIN.<init>(BB)V
		// 170
		virtualMethodRef 1.16.1()V;		// javacard/security/KeyPair.genKeyPair()V
		// 171
		staticMethodRef 1.15.0(BZ)Ljavacard/security/Signature;;		// javacard/security/Signature.getInstance(BZ)Ljavacard/security/Signature;
			.descriptor	Ljavacard/security/Signature;	1.15;

		// 172
		virtualMethodRef 1.15.3(Ljavacard/security/Key;B)V;		// javacard/security/Signature.init(Ljavacard/security/Key;B)V
			.descriptor	Ljavacard/security/Key;	1.0;

		// 173
		virtualMethodRef 1.15.5([BSS[BS)S;		// javacard/security/Signature.sign([BSS[BS)S
		// 174
		virtualMethodRef 2.10.1()[B;		// javacard/framework/APDU.getBuffer()[B
		// 175
		virtualMethodRef 2.9.8([BSB)V;		// javacard/framework/OwnerPIN.update([BSB)V
		// 176
		virtualMethodRef 2.10.6()S;		// javacard/framework/APDU.setIncomingAndReceive()S
		// 177
		virtualMethodRef CryptoManager/encrypt([BSS[BS[BS)V;
		// 178
		virtualMethodRef 2.9.4()Z;		// javacard/framework/OwnerPIN.isValidated()Z
		// 179
		virtualMethodRef 2.9.1([BSB)Z;		// javacard/framework/OwnerPIN.check([BSB)Z
		// 180
		virtualMethodRef CryptoManager/deriveKeyFromPIN([BSB[BSS)V;
		// 181
		virtualMethodRef CardModel/isMasterKeyWrapped()Z;
		// 182
		virtualMethodRef CardModel/getWrappedMasterKey()[B;
		// 183
		virtualMethodRef CryptoManager/unwrapMasterKey([BS[BS)V;
		// 184
		virtualMethodRef CardModel/ensureMasterKey(LParkCard/CryptoManager;)V;
		// 185
		virtualMethodRef 2.9.2()B;		// javacard/framework/OwnerPIN.getTriesRemaining()B
		// 186
		virtualMethodRef 2.9.6()V;		// javacard/framework/OwnerPIN.resetAndUnblock()V
		// 187
		virtualMethodRef CardModel/setMasterKeyWrapped(Z)V;
		// 188
		virtualMethodRef CardModel/isMasterKeyWrappedAdmin()Z;
		// 189
		virtualMethodRef CardModel/getWrappedMasterKeyAdmin()[B;
		// 190
		virtualMethodRef CardModel/ensureMasterKeyWithAdmin(LParkCard/CryptoManager;Z)V;
		// 191
		staticMethodRef PinManager/syncMasterKeyToUserPIN()V;
	}

	.class public CardModel 0 extends 0.0 {		// extends java/lang/Object

		.fields {
			 byte[] customerID 0;		// [B
			private 1.16 rsaKeyPair 1;		// Ljavacard/security/KeyPair;
			private 1.8 privateKey 2;		// Ljavacard/security/RSAPrivateKey;
			private 1.9 publicKey 3;		// Ljavacard/security/RSAPublicKey;
			 byte[] name 4;		// [B
			 byte[] dateOfBirth 5;		// [B
			 byte[] phoneNumber 6;		// [B
			 byte[] balance 7;		// [B
			 byte[] customerPhoto 8;		// [B
			 byte[] decryptedPhoto 9;		// [B
			 byte[] gameList 10;		// [B
			 short[] gameCountRef 11;		// [S
			 byte[] iv 12;		// [B
			 byte[] salt 13;		// [B
			 byte[] wrappedMasterKey 14;		// [B
			 byte[] wrappedMasterKeyAdmin 15;		// [B
			private byte[] tempDecryptBuffer 16;		// [B
			 short photoLength 17;		// S
			 short photoWriteOffset 18;		// S
			 short actualPhotoLength 19;		// S
			 short encryptedPhotoLength 20;		// S
			 boolean masterKeyWrapped 21;		// Z
			 boolean masterKeyWrappedAdmin 22;		// Z
			 boolean dataReady 23;		// Z
			 boolean dataEncrypted 24;		// Z
			 boolean rsaKeyReady 25;		// Z
			private static final short LEN_CUSTOMER_ID = 15;		// S
			private static final short LEN_NAME = 64;		// S
			private static final short LEN_DOB = 16;		// S
			private static final short LEN_PHONE = 16;		// S
			private static final short LEN_BALANCE = 16;		// S
			private static final short MAX_PHOTO_SIZE = 8000;		// S
			private static final short IV_SIZE = 16;		// S
			private static final short SALT_SIZE = 16;		// S
			private static final short RSA_KEY_SIZE = 1024;		// S
			private static final short RSA_SIG_SIZE = 128;		// S
			private static final short MAX_GAMES = 50;		// S
			private static final short GAME_ENTRY_SIZE = 3;		// S
			private static final short GAME_LIST_SIZE = 160;		// S
			private static final short MAX_BALANCE = 30000;		// S
			private static final short AES_KEY_SIZE = 16;		// S
		}

		.publicMethodTable 1 {
			equals(Ljava/lang/Object;)Z;
			ensureMasterKey(LParkCard/CryptoManager;)V;
			isDataReady()Z;
			setDataReady(Z)V;
			getIV()[B;
			getSalt()[B;
			isDataEncrypted()Z;
			isRSAKeyReady()Z;
			getWrappedMasterKey()[B;
			isMasterKeyWrapped()Z;
			setMasterKeyWrapped(Z)V;
			getWrappedMasterKeyAdmin()[B;
			isMasterKeyWrappedAdmin()Z;
			setMasterKeyWrappedAdmin(Z)V;
			ensureMasterKeyWithAdmin(LParkCard/CryptoManager;Z)V;
			syncMasterKeyToOtherType(LParkCard/CryptoManager;Z)V;
			setCustomerID([BSS)V;
			getCustomerID([BS)V;
			generateRSAKeyPair()V;
			getPublicKeyExponent([BS)S;
			getPublicKeyModulus([BS)S;
			setRSAExponent([BSS)V;
			setRSAModulus([BSS)V;
			signChallenge([BSS[BS)S;
			writeCustomerInfo(Ljavacard/framework/APDU;LParkCard/CryptoManager;)V;
			readAllData(Ljavacard/framework/APDU;LParkCard/CryptoManager;)V;
			startPhotoWrite()V;
			writePhotoChunk(Ljavacard/framework/APDU;)V;
			finishPhotoWrite(Ljavacard/framework/APDU;LParkCard/CryptoManager;)V;
			readPhotoChunk(Ljavacard/framework/APDU;LParkCard/CryptoManager;)V;
			initializeBalance(LParkCard/CryptoManager;)V;
			rechargeBalance(Ljavacard/framework/APDU;LParkCard/CryptoManager;)V;
			checkBalance(Ljavacard/framework/APDU;LParkCard/CryptoManager;)V;
			makePayment(Ljavacard/framework/APDU;LParkCard/CryptoManager;)V;
			reEncryptAllData(LParkCard/CryptoManager;LParkCard/CryptoManager;)V;
		}

		.packageMethodTable 0 {
		}

		.method public <init>()V 0 {
			.stack 5;
			.locals 0;

				L0:	aload_0;
					invokespecial 58;		// java/lang/Object.<init>()V
					aload_0;
					bspush 15;
					newarray 11;
					putfield_a 0;		// reference ParkCard/CardModel.customerID
					aload_0;
					new 61;		// javacard/security/KeyPair
					dup;
					sconst_1;
					sspush 1024;
					invokespecial 66;		// javacard/security/KeyPair.<init>(BS)V
					putfield_a 1;		// reference ParkCard/CardModel.rsaKeyPair
					aload_0;
					getfield_a_this 1;		// reference ParkCard/CardModel.rsaKeyPair
					invokevirtual 59;		// javacard/security/KeyPair.getPrivate()Ljavacard/security/PrivateKey;
					checkcast 0 60;		// T_CLASSORINTERFACE javacard/security/RSAPrivateKey
					putfield_a 2;		// reference ParkCard/CardModel.privateKey
					aload_0;
					getfield_a_this 1;		// reference ParkCard/CardModel.rsaKeyPair
					invokevirtual 62;		// javacard/security/KeyPair.getPublic()Ljavacard/security/PublicKey;
					checkcast 0 63;		// T_CLASSORINTERFACE javacard/security/RSAPublicKey
					putfield_a 3;		// reference ParkCard/CardModel.publicKey
					aload_0;
					bspush 64;
					newarray 11;
					putfield_a 4;		// reference ParkCard/CardModel.name
					aload_0;
					bspush 16;
					newarray 11;
					putfield_a 5;		// reference ParkCard/CardModel.dateOfBirth
					aload_0;
					bspush 16;
					newarray 11;
					putfield_a 6;		// reference ParkCard/CardModel.phoneNumber
					aload_0;
					bspush 16;
					newarray 11;
					putfield_a 7;		// reference ParkCard/CardModel.balance
					aload_0;
					sspush 8000;
					newarray 11;
					putfield_a 8;		// reference ParkCard/CardModel.customerPhoto
					aload_0;
					sspush 8000;
					newarray 11;
					putfield_a 9;		// reference ParkCard/CardModel.decryptedPhoto
					aload_0;
					sconst_0;
					putfield_s 10;		// short ParkCard/CardModel.photoLength
					aload_0;
					sconst_0;
					putfield_s 11;		// short ParkCard/CardModel.photoWriteOffset
					aload_0;
					sconst_0;
					putfield_s 12;		// short ParkCard/CardModel.actualPhotoLength
					aload_0;
					sconst_0;
					putfield_s 13;		// short ParkCard/CardModel.encryptedPhotoLength
					aload_0;
					sspush 160;
					newarray 11;
					putfield_a 14;		// reference ParkCard/CardModel.gameList
					aload_0;
					sconst_1;
					newarray 12;
					putfield_a 15;		// reference ParkCard/CardModel.gameCountRef
					getfield_a_this 15;		// reference ParkCard/CardModel.gameCountRef
					sconst_0;
					sconst_0;
					sastore;
					aload_0;
					bspush 16;
					newarray 11;
					putfield_a 16;		// reference ParkCard/CardModel.iv
					aload_0;
					bspush 16;
					newarray 11;
					putfield_a 17;		// reference ParkCard/CardModel.salt
					aload_0;
					invokespecial 80;		// ParkCard/CardModel.generateIVAndSalt()V
					aload_0;
					sconst_0;
					putfield_b 18;		// boolean ParkCard/CardModel.dataReady
					aload_0;
					sconst_0;
					putfield_b 19;		// boolean ParkCard/CardModel.dataEncrypted
					aload_0;
					sconst_0;
					putfield_b 20;		// boolean ParkCard/CardModel.rsaKeyReady
					aload_0;
					bspush 16;
					newarray 11;
					putfield_a 21;		// reference ParkCard/CardModel.wrappedMasterKey
					aload_0;
					sconst_0;
					putfield_b 22;		// boolean ParkCard/CardModel.masterKeyWrapped
					aload_0;
					bspush 16;
					newarray 11;
					putfield_a 23;		// reference ParkCard/CardModel.wrappedMasterKeyAdmin
					aload_0;
					sconst_0;
					putfield_b 24;		// boolean ParkCard/CardModel.masterKeyWrappedAdmin
					aload_0;
					bspush 64;
					sconst_2;
					invokestatic 77;		// javacard/framework/JCSystem.makeTransientByteArray(SB)[B
					putfield_a 25;		// reference ParkCard/CardModel.tempDecryptBuffer
					return;
		}

		.method private generateIVAndSalt()V {
			.stack 4;
			.locals 1;

				L0:	sconst_2;
					invokestatic 83;		// javacard/security/RandomData.getInstance(B)Ljavacard/security/RandomData;
					astore_1;
				L1:	aload_1;
					getfield_a_this 16;		// reference ParkCard/CardModel.iv
					sconst_0;
					bspush 16;
					invokevirtual 86;		// javacard/security/RandomData.generateData([BSS)V
					aload_1;
					getfield_a_this 17;		// reference ParkCard/CardModel.salt
					sconst_0;
					bspush 16;
					invokevirtual 86;		// javacard/security/RandomData.generateData([BSS)V
					return;
		}

		.method public ensureMasterKey(LParkCard/CryptoManager;)V 1 {
			.stack 7;
			.locals 2;

				L0:	getfield_b_this 22;		// boolean ParkCard/CardModel.masterKeyWrapped
					ifeq L2;
				L1:	return;
				L2:	bspush 16;
					sconst_2;
					invokestatic 77;		// javacard/framework/JCSystem.makeTransientByteArray(SB)[B
					astore_2;
				L3:	sconst_2;
					invokestatic 83;		// javacard/security/RandomData.getInstance(B)Ljavacard/security/RandomData;
					astore_3;
				L4:	aload_3;
					aload_2;
					sconst_0;
					bspush 16;
					invokevirtual 86;		// javacard/security/RandomData.generateData([BSS)V
					aload_1;
					aload_2;
					sconst_0;
					getfield_a_this 21;		// reference ParkCard/CardModel.wrappedMasterKey
					sconst_0;
					getfield_a_this 16;		// reference ParkCard/CardModel.iv
					sconst_0;
					invokevirtual 154;		// ParkCard/CryptoManager.wrapMasterKey([BS[BS[BS)V
					aload_0;
					sconst_1;
					putfield_b 22;		// boolean ParkCard/CardModel.masterKeyWrapped
					aload_2;
					sconst_0;
					bspush 16;
					sconst_0;
					invokestatic 155;		// javacard/framework/Util.arrayFillNonAtomic([BSSB)S
					pop;
					return;
		}

		.method public isDataReady()Z 2 {
			.stack 1;
			.locals 0;

				L0:	getfield_b_this 18;		// boolean ParkCard/CardModel.dataReady
					sreturn;
		}

		.method public setDataReady(Z)V 3 {
			.stack 2;
			.locals 0;

				L0:	aload_0;
					sload_1;
					putfield_b 18;		// boolean ParkCard/CardModel.dataReady
					return;
		}

		.method public getIV()[B 4 {
			.stack 1;
			.locals 0;

				L0:	getfield_a_this 16;		// reference ParkCard/CardModel.iv
					areturn;
		}

		.method public getSalt()[B 5 {
			.stack 1;
			.locals 0;

				L0:	getfield_a_this 17;		// reference ParkCard/CardModel.salt
					areturn;
		}

		.method public isDataEncrypted()Z 6 {
			.stack 1;
			.locals 0;

				L0:	getfield_b_this 19;		// boolean ParkCard/CardModel.dataEncrypted
					sreturn;
		}

		.method public isRSAKeyReady()Z 7 {
			.stack 1;
			.locals 0;

				L0:	getfield_b_this 20;		// boolean ParkCard/CardModel.rsaKeyReady
					sreturn;
		}

		.method public getWrappedMasterKey()[B 8 {
			.stack 1;
			.locals 0;

				L0:	getfield_a_this 21;		// reference ParkCard/CardModel.wrappedMasterKey
					areturn;
		}

		.method public isMasterKeyWrapped()Z 9 {
			.stack 1;
			.locals 0;

				L0:	getfield_b_this 22;		// boolean ParkCard/CardModel.masterKeyWrapped
					sreturn;
		}

		.method public setMasterKeyWrapped(Z)V 10 {
			.stack 2;
			.locals 0;

				L0:	aload_0;
					sload_1;
					putfield_b 22;		// boolean ParkCard/CardModel.masterKeyWrapped
					return;
		}

		.method public getWrappedMasterKeyAdmin()[B 11 {
			.stack 1;
			.locals 0;

				L0:	getfield_a_this 23;		// reference ParkCard/CardModel.wrappedMasterKeyAdmin
					areturn;
		}

		.method public isMasterKeyWrappedAdmin()Z 12 {
			.stack 1;
			.locals 0;

				L0:	getfield_b_this 24;		// boolean ParkCard/CardModel.masterKeyWrappedAdmin
					sreturn;
		}

		.method public setMasterKeyWrappedAdmin(Z)V 13 {
			.stack 2;
			.locals 0;

				L0:	aload_0;
					sload_1;
					putfield_b 24;		// boolean ParkCard/CardModel.masterKeyWrappedAdmin
					return;
		}

		.method public ensureMasterKeyWithAdmin(LParkCard/CryptoManager;Z)V 14 {
			.stack 7;
			.locals 2;

				L0:	bspush 16;
					sconst_2;
					invokestatic 77;		// javacard/framework/JCSystem.makeTransientByteArray(SB)[B
					astore_3;
				L1:	sload_2;
					ifeq L8;
				L2:	getfield_b_this 24;		// boolean ParkCard/CardModel.masterKeyWrappedAdmin
					ifeq L4;
				L3:	return;
				L4:	getfield_b_this 22;		// boolean ParkCard/CardModel.masterKeyWrapped
					ifeq L5;
				L5:	sconst_2;
					invokestatic 83;		// javacard/security/RandomData.getInstance(B)Ljavacard/security/RandomData;
					astore 4;
				L6:	aload 4;
					aload_3;
					sconst_0;
					bspush 16;
					invokevirtual 86;		// javacard/security/RandomData.generateData([BSS)V
					aload_1;
					aload_3;
					sconst_0;
					getfield_a_this 23;		// reference ParkCard/CardModel.wrappedMasterKeyAdmin
					sconst_0;
					getfield_a_this 16;		// reference ParkCard/CardModel.iv
					sconst_0;
					invokevirtual 154;		// ParkCard/CryptoManager.wrapMasterKey([BS[BS[BS)V
					aload_0;
					sconst_1;
					putfield_b 24;		// boolean ParkCard/CardModel.masterKeyWrappedAdmin
				L7:	goto L13;
				L8:	getfield_b_this 22;		// boolean ParkCard/CardModel.masterKeyWrapped
					ifeq L10;
				L9:	return;
				L10:	getfield_b_this 24;		// boolean ParkCard/CardModel.masterKeyWrappedAdmin
					ifeq L11;
				L11:	sconst_2;
					invokestatic 83;		// javacard/security/RandomData.getInstance(B)Ljavacard/security/RandomData;
					astore 4;
				L12:	aload 4;
					aload_3;
					sconst_0;
					bspush 16;
					invokevirtual 86;		// javacard/security/RandomData.generateData([BSS)V
					aload_1;
					aload_3;
					sconst_0;
					getfield_a_this 21;		// reference ParkCard/CardModel.wrappedMasterKey
					sconst_0;
					getfield_a_this 16;		// reference ParkCard/CardModel.iv
					sconst_0;
					invokevirtual 154;		// ParkCard/CryptoManager.wrapMasterKey([BS[BS[BS)V
					aload_0;
					sconst_1;
					putfield_b 22;		// boolean ParkCard/CardModel.masterKeyWrapped
				L13:	aload_3;
					sconst_0;
					bspush 16;
					sconst_0;
					invokestatic 155;		// javacard/framework/Util.arrayFillNonAtomic([BSSB)S
					pop;
					return;
		}

		.method public syncMasterKeyToOtherType(LParkCard/CryptoManager;Z)V 15 {
			.stack 5;
			.locals 0;

				L0:	aload_1;
					invokevirtual 160;		// ParkCard/CryptoManager.isKeyReady()Z
					ifne L2;
				L1:	return;
				L2:	sload_2;
					ifeq L5;
				L3:	getfield_b_this 22;		// boolean ParkCard/CardModel.masterKeyWrapped
					ifne L7;
				L4:	aload_1;
					getfield_a_this 21;		// reference ParkCard/CardModel.wrappedMasterKey
					sconst_0;
					getfield_a_this 16;		// reference ParkCard/CardModel.iv
					sconst_0;
					invokevirtual 161;		// ParkCard/CryptoManager.wrapLoadedMasterKey([BS[BS)V
					aload_0;
					sconst_1;
					putfield_b 22;		// boolean ParkCard/CardModel.masterKeyWrapped
					goto L7;
				L5:	getfield_b_this 24;		// boolean ParkCard/CardModel.masterKeyWrappedAdmin
					ifne L7;
				L6:	aload_1;
					getfield_a_this 23;		// reference ParkCard/CardModel.wrappedMasterKeyAdmin
					sconst_0;
					getfield_a_this 16;		// reference ParkCard/CardModel.iv
					sconst_0;
					invokevirtual 161;		// ParkCard/CryptoManager.wrapLoadedMasterKey([BS[BS)V
					aload_0;
					sconst_1;
					putfield_b 24;		// boolean ParkCard/CardModel.masterKeyWrappedAdmin
				L7:	return;
		}

		.method public setCustomerID([BSS)V 16 {
			.stack 5;
			.locals 0;

				L0:	sload_3;
					bspush 15;
					if_scmple L2;
				L1:	sspush 26368;
					invokestatic 162;		// javacard/framework/ISOException.throwIt(S)V
				L2:	getfield_a_this 0;		// reference ParkCard/CardModel.customerID
					sconst_0;
					bspush 15;
					sconst_0;
					invokestatic 155;		// javacard/framework/Util.arrayFillNonAtomic([BSSB)S
					pop;
					aload_1;
					sload_2;
					getfield_a_this 0;		// reference ParkCard/CardModel.customerID
					sconst_0;
					sload_3;
					invokestatic 163;		// javacard/framework/Util.arrayCopyNonAtomic([BS[BSS)S
					pop;
					return;
		}

		.method public getCustomerID([BS)V 17 {
			.stack 5;
			.locals 0;

				L0:	getfield_a_this 0;		// reference ParkCard/CardModel.customerID
					sconst_0;
					aload_1;
					sload_2;
					bspush 15;
					invokestatic 163;		// javacard/framework/Util.arrayCopyNonAtomic([BS[BSS)S
					pop;
					return;
		}

		.method public generateRSAKeyPair()V 18 {
			.stack 2;
			.locals 0;

				L0:	getfield_a_this 1;		// reference ParkCard/CardModel.rsaKeyPair
					invokevirtual 170;		// javacard/security/KeyPair.genKeyPair()V
					aload_0;
					sconst_1;
					putfield_b 20;		// boolean ParkCard/CardModel.rsaKeyReady
					return;
		}

		.method public getPublicKeyExponent([BS)S 19 {
			.stack 3;
			.locals 0;

				L0:	getfield_b_this 20;		// boolean ParkCard/CardModel.rsaKeyReady
					ifne L2;
				L1:	sspush 27013;
					invokestatic 162;		// javacard/framework/ISOException.throwIt(S)V
				L2:	getfield_a_this 3;		// reference ParkCard/CardModel.publicKey
					aload_1;
					sload_2;
					invokeinterface 3 63 4;		// javacard/security/RSAPublicKey
					sreturn;
		}

		.method public getPublicKeyModulus([BS)S 20 {
			.stack 3;
			.locals 0;

				L0:	getfield_b_this 20;		// boolean ParkCard/CardModel.rsaKeyReady
					ifne L2;
				L1:	sspush 27013;
					invokestatic 162;		// javacard/framework/ISOException.throwIt(S)V
				L2:	getfield_a_this 3;		// reference ParkCard/CardModel.publicKey
					aload_1;
					sload_2;
					invokeinterface 3 63 5;		// javacard/security/RSAPublicKey
					sreturn;
		}

		.method public setRSAExponent([BSS)V 21 {
			.stack 4;
			.locals 0;

				L0:	getfield_a_this 2;		// reference ParkCard/CardModel.privateKey
					aload_1;
					sload_2;
					sload_3;
					invokeinterface 4 60 6;		// javacard/security/RSAPrivateKey
					return;
		}

		.method public setRSAModulus([BSS)V 22 {
			.stack 4;
			.locals 0;

				L0:	getfield_a_this 2;		// reference ParkCard/CardModel.privateKey
					aload_1;
					sload_2;
					sload_3;
					invokeinterface 4 60 7;		// javacard/security/RSAPrivateKey
					aload_0;
					sconst_1;
					putfield_b 20;		// boolean ParkCard/CardModel.rsaKeyReady
					return;
		}

		.method public signChallenge([BSS[BS)S 23 {
			.stack 6;
			.locals 1;

				L0:	getfield_b_this 20;		// boolean ParkCard/CardModel.rsaKeyReady
					ifne L2;
				L1:	sspush 27013;
					invokestatic 162;		// javacard/framework/ISOException.throwIt(S)V
				L2:	bspush 10;
					sconst_0;
					invokestatic 171;		// javacard/security/Signature.getInstance(BZ)Ljavacard/security/Signature;
					astore 6;
				L3:	aload 6;
					getfield_a_this 2;		// reference ParkCard/CardModel.privateKey
					sconst_1;
					invokevirtual 172;		// javacard/security/Signature.init(Ljavacard/security/Key;B)V
					aload 6;
					aload_1;
					sload_2;
					sload_3;
					aload 4;
					sload 5;
					invokevirtual 173;		// javacard/security/Signature.sign([BSS[BS)S
					sreturn;
		}

		.method public writeCustomerInfo(Ljavacard/framework/APDU;LParkCard/CryptoManager;)V 24 {
			.stack 8;
			.locals 2;

			.descriptor	Ljavacard/framework/APDU;	2.10;

				L0:	aload_1;
					invokevirtual 174;		// javacard/framework/APDU.getBuffer()[B
					astore_3;
				L1:	aload_1;
					invokevirtual 176;		// javacard/framework/APDU.setIncomingAndReceive()S
					pop;
					sconst_5;
					sstore 4;
				L2:	aload_2;
					aload_3;
					sload 4;
					bspush 64;
					getfield_a_this 4;		// reference ParkCard/CardModel.name
					sconst_0;
					getfield_a_this 16;		// reference ParkCard/CardModel.iv
					sconst_0;
					invokevirtual 177;		// ParkCard/CryptoManager.encrypt([BSS[BS[BS)V
					sinc 4 64;
					aload_2;
					aload_3;
					sload 4;
					bspush 16;
					getfield_a_this 5;		// reference ParkCard/CardModel.dateOfBirth
					sconst_0;
					getfield_a_this 16;		// reference ParkCard/CardModel.iv
					sconst_0;
					invokevirtual 177;		// ParkCard/CryptoManager.encrypt([BSS[BS[BS)V
					sinc 4 16;
					aload_2;
					aload_3;
					sload 4;
					bspush 16;
					getfield_a_this 6;		// reference ParkCard/CardModel.phoneNumber
					sconst_0;
					getfield_a_this 16;		// reference ParkCard/CardModel.iv
					sconst_0;
					invokevirtual 177;		// ParkCard/CryptoManager.encrypt([BSS[BS[BS)V
					aload_0;
					sconst_1;
					putfield_b 19;		// boolean ParkCard/CardModel.dataEncrypted
					return;
		}

		.method public readAllData(Ljavacard/framework/APDU;LParkCard/CryptoManager;)V 25 {
			.stack 8;
			.locals 2;

			.descriptor	Ljavacard/framework/APDU;	2.10;

				L0:	aload_1;
					invokevirtual 174;		// javacard/framework/APDU.getBuffer()[B
					astore_3;
				L1:	sconst_0;
					sstore 4;
				L2:	getfield_a_this 0;		// reference ParkCard/CardModel.customerID
					sconst_0;
					aload_3;
					sload 4;
					bspush 15;
					invokestatic 163;		// javacard/framework/Util.arrayCopyNonAtomic([BS[BSS)S
					pop;
					sinc 4 15;
					aload_2;
					getfield_a_this 4;		// reference ParkCard/CardModel.name
					sconst_0;
					bspush 64;
					getfield_a_this 25;		// reference ParkCard/CardModel.tempDecryptBuffer
					sconst_0;
					getfield_a_this 16;		// reference ParkCard/CardModel.iv
					sconst_0;
					invokevirtual 50;		// ParkCard/CryptoManager.decrypt([BSS[BS[BS)V
					getfield_a_this 25;		// reference ParkCard/CardModel.tempDecryptBuffer
					sconst_0;
					aload_3;
					sload 4;
					bspush 64;
					invokestatic 163;		// javacard/framework/Util.arrayCopyNonAtomic([BS[BSS)S
					pop;
					sinc 4 64;
					aload_2;
					getfield_a_this 5;		// reference ParkCard/CardModel.dateOfBirth
					sconst_0;
					bspush 16;
					getfield_a_this 25;		// reference ParkCard/CardModel.tempDecryptBuffer
					sconst_0;
					getfield_a_this 16;		// reference ParkCard/CardModel.iv
					sconst_0;
					invokevirtual 50;		// ParkCard/CryptoManager.decrypt([BSS[BS[BS)V
					getfield_a_this 25;		// reference ParkCard/CardModel.tempDecryptBuffer
					sconst_0;
					aload_3;
					sload 4;
					bspush 16;
					invokestatic 163;		// javacard/framework/Util.arrayCopyNonAtomic([BS[BSS)S
					pop;
					sinc 4 16;
					aload_2;
					getfield_a_this 6;		// reference ParkCard/CardModel.phoneNumber
					sconst_0;
					bspush 16;
					getfield_a_this 25;		// reference ParkCard/CardModel.tempDecryptBuffer
					sconst_0;
					getfield_a_this 16;		// reference ParkCard/CardModel.iv
					sconst_0;
					invokevirtual 50;		// ParkCard/CryptoManager.decrypt([BSS[BS[BS)V
					getfield_a_this 25;		// reference ParkCard/CardModel.tempDecryptBuffer
					sconst_0;
					aload_3;
					sload 4;
					bspush 16;
					invokestatic 163;		// javacard/framework/Util.arrayCopyNonAtomic([BS[BSS)S
					pop;
					sinc 4 16;
					aload_3;
					sload 4;
					sinc 4 1;
					getfield_s_this 10;		// short ParkCard/CardModel.photoLength
					bspush 8;
					sshr;
					s2b;
					bastore;
					aload_3;
					sload 4;
					sinc 4 1;
					getfield_s_this 10;		// short ParkCard/CardModel.photoLength
					s2b;
					bastore;
					aload_1;
					invokevirtual 51;		// javacard/framework/APDU.setOutgoing()S
					pop;
					aload_1;
					sload 4;
					invokevirtual 52;		// javacard/framework/APDU.setOutgoingLength(S)V
					aload_1;
					aload_3;
					sconst_0;
					sload 4;
					invokevirtual 53;		// javacard/framework/APDU.sendBytesLong([BSS)V
					return;
		}

		.method public startPhotoWrite()V 26 {
			.stack 4;
			.locals 0;

				L0:	aload_0;
					sconst_0;
					putfield_s 11;		// short ParkCard/CardModel.photoWriteOffset
					aload_0;
					sconst_0;
					putfield_s 10;		// short ParkCard/CardModel.photoLength
					aload_0;
					sconst_0;
					putfield_s 12;		// short ParkCard/CardModel.actualPhotoLength
					aload_0;
					sconst_0;
					putfield_s 13;		// short ParkCard/CardModel.encryptedPhotoLength
					getfield_a_this 8;		// reference ParkCard/CardModel.customerPhoto
					sconst_0;
					sspush 8000;
					sconst_0;
					invokestatic 155;		// javacard/framework/Util.arrayFillNonAtomic([BSSB)S
					pop;
					return;
		}

		.method public writePhotoChunk(Ljavacard/framework/APDU;)V 27 {
			.stack 5;
			.locals 2;

			.descriptor	Ljavacard/framework/APDU;	2.10;

				L0:	aload_1;
					invokevirtual 176;		// javacard/framework/APDU.setIncomingAndReceive()S
					sstore_2;
				L1:	aload_1;
					invokevirtual 174;		// javacard/framework/APDU.getBuffer()[B
					astore_3;
				L2:	getfield_s_this 11;		// short ParkCard/CardModel.photoWriteOffset
					sload_2;
					sadd;
					sspush 8000;
					if_scmple L4;
				L3:	sspush 26368;
					invokestatic 162;		// javacard/framework/ISOException.throwIt(S)V
				L4:	aload_3;
					sconst_5;
					getfield_a_this 8;		// reference ParkCard/CardModel.customerPhoto
					getfield_s_this 11;		// short ParkCard/CardModel.photoWriteOffset
					sload_2;
					invokestatic 163;		// javacard/framework/Util.arrayCopyNonAtomic([BS[BSS)S
					pop;
					aload_0;
					dup;
					getfield_s 11;		// short ParkCard/CardModel.photoWriteOffset
					sload_2;
					sadd;
					putfield_s 11;		// short ParkCard/CardModel.photoWriteOffset
					return;
		}

		.method public finishPhotoWrite(Ljavacard/framework/APDU;LParkCard/CryptoManager;)V 28 {
			.stack 6;
			.locals 0;

			.descriptor	Ljavacard/framework/APDU;	2.10;

				L0:	aload_0;
					getfield_s_this 11;		// short ParkCard/CardModel.photoWriteOffset
					putfield_s 12;		// short ParkCard/CardModel.actualPhotoLength
					aload_0;
					getfield_s_this 12;		// short ParkCard/CardModel.actualPhotoLength
					s2i;
					bipush 15;
					iadd;
					bipush 16;
					idiv;
					bipush 16;
					imul;
					i2s;
					putfield_s 13;		// short ParkCard/CardModel.encryptedPhotoLength
					getfield_s_this 13;		// short ParkCard/CardModel.encryptedPhotoLength
					getfield_s_this 12;		// short ParkCard/CardModel.actualPhotoLength
					if_scmple L2;
				L1:	getfield_a_this 8;		// reference ParkCard/CardModel.customerPhoto
					getfield_s_this 12;		// short ParkCard/CardModel.actualPhotoLength
					getfield_s_this 13;		// short ParkCard/CardModel.encryptedPhotoLength
					getfield_s_this 12;		// short ParkCard/CardModel.actualPhotoLength
					ssub;
					sconst_0;
					invokestatic 155;		// javacard/framework/Util.arrayFillNonAtomic([BSSB)S
					pop;
				L2:	aload_2;
					ifnull L5;
				L3:	aload_2;
					invokevirtual 160;		// ParkCard/CryptoManager.isKeyReady()Z
					ifeq L5;
				L4:	aload_2;
					getfield_a_this 8;		// reference ParkCard/CardModel.customerPhoto
					sconst_0;
					getfield_s_this 13;		// short ParkCard/CardModel.encryptedPhotoLength
					getfield_a_this 8;		// reference ParkCard/CardModel.customerPhoto
					sconst_0;
					invokevirtual 54;		// ParkCard/CryptoManager.encryptPhotoECB([BSS[BS)V
				L5:	aload_0;
					getfield_s_this 13;		// short ParkCard/CardModel.encryptedPhotoLength
					putfield_s 10;		// short ParkCard/CardModel.photoLength
					aload_0;
					sconst_0;
					putfield_s 11;		// short ParkCard/CardModel.photoWriteOffset
					return;
		}

		.method public readPhotoChunk(Ljavacard/framework/APDU;LParkCard/CryptoManager;)V 29 {
			.stack 6;
			.locals 5;

			.descriptor	Ljavacard/framework/APDU;	2.10;

				L0:	aload_1;
					invokevirtual 174;		// javacard/framework/APDU.getBuffer()[B
					astore_3;
				L1:	aload_3;
					sconst_2;
					baload;
					bspush 8;
					sshl;
					aload_3;
					sconst_3;
					baload;
					sspush 255;
					sand;
					sor;
					sstore 4;
				L2:	aload_1;
					invokevirtual 51;		// javacard/framework/APDU.setOutgoing()S
					sstore 5;
				L3:	sload 5;
					ifeq L5;
				L4:	sload 5;
					sspush 200;
					if_scmple L6;
				L5:	sspush 200;
					sstore 5;
				L6:	getfield_s_this 10;		// short ParkCard/CardModel.photoLength
					ifeq L8;
				L7:	sload 4;
					getfield_s_this 12;		// short ParkCard/CardModel.actualPhotoLength
					if_scmplt L12;
				L8:	sload 4;
					getfield_s_this 12;		// short ParkCard/CardModel.actualPhotoLength
					if_scmplt L10;
				L9:	sspush 27270;
					goto L11;
				L10:	sspush 27266;
				L11:	invokestatic 162;		// javacard/framework/ISOException.throwIt(S)V
				L12:	aload_2;
					ifnull L16;
				L13:	aload_2;
					invokevirtual 160;		// ParkCard/CryptoManager.isKeyReady()Z
					ifeq L16;
				L14:	getfield_s_this 10;		// short ParkCard/CardModel.photoLength
					ifle L16;
				L15:	aload_2;
					getfield_a_this 8;		// reference ParkCard/CardModel.customerPhoto
					sconst_0;
					getfield_s_this 10;		// short ParkCard/CardModel.photoLength
					getfield_a_this 9;		// reference ParkCard/CardModel.decryptedPhoto
					sconst_0;
					invokevirtual 55;		// ParkCard/CryptoManager.decryptPhotoECB([BSS[BS)V
				L16:	getfield_s_this 12;		// short ParkCard/CardModel.actualPhotoLength
					sload 4;
					ssub;
					sstore 6;
				L17:	sload 5;
					sload 6;
					if_scmpge L19;
				L18:	sload 5;
					goto L20;
				L19:	sload 6;
				L20:	sstore 7;
				L21:	aload_1;
					sload 7;
					invokevirtual 52;		// javacard/framework/APDU.setOutgoingLength(S)V
					aload_1;
					getfield_a_this 9;		// reference ParkCard/CardModel.decryptedPhoto
					sload 4;
					sload 7;
					invokevirtual 53;		// javacard/framework/APDU.sendBytesLong([BSS)V
					return;
		}

		.method public initializeBalance(LParkCard/CryptoManager;)V 30 {
			.stack 8;
			.locals 0;

				L0:	getfield_a_this 25;		// reference ParkCard/CardModel.tempDecryptBuffer
					sconst_0;
					bspush 16;
					sconst_0;
					invokestatic 155;		// javacard/framework/Util.arrayFillNonAtomic([BSSB)S
					pop;
					getfield_a_this 25;		// reference ParkCard/CardModel.tempDecryptBuffer
					sconst_0;
					sconst_0;
					bastore;
					getfield_a_this 25;		// reference ParkCard/CardModel.tempDecryptBuffer
					sconst_1;
					sconst_0;
					bastore;
					aload_1;
					getfield_a_this 25;		// reference ParkCard/CardModel.tempDecryptBuffer
					sconst_0;
					bspush 16;
					getfield_a_this 7;		// reference ParkCard/CardModel.balance
					sconst_0;
					getfield_a_this 16;		// reference ParkCard/CardModel.iv
					sconst_0;
					invokevirtual 177;		// ParkCard/CryptoManager.encrypt([BSS[BS[BS)V
					aload_0;
					sconst_1;
					putfield_b 19;		// boolean ParkCard/CardModel.dataEncrypted
					return;
		}

		.method public rechargeBalance(Ljavacard/framework/APDU;LParkCard/CryptoManager;)V 31 {
			.stack 8;
			.locals 5;

			.descriptor	Ljavacard/framework/APDU;	2.10;

				L0:	aload_1;
					invokevirtual 176;		// javacard/framework/APDU.setIncomingAndReceive()S
					sstore_3;
				L1:	sload_3;
					sconst_2;
					if_scmpeq L3;
				L2:	sspush 26368;
					invokestatic 162;		// javacard/framework/ISOException.throwIt(S)V
				L3:	aload_1;
					invokevirtual 174;		// javacard/framework/APDU.getBuffer()[B
					astore 4;
				L4:	aload 4;
					sconst_5;
					baload;
					bspush 8;
					sshl;
					aload 4;
					bspush 6;
					baload;
					sspush 255;
					sand;
					sor;
					sstore 5;
				L5:	aload_2;
					getfield_a_this 7;		// reference ParkCard/CardModel.balance
					sconst_0;
					bspush 16;
					getfield_a_this 25;		// reference ParkCard/CardModel.tempDecryptBuffer
					sconst_0;
					getfield_a_this 16;		// reference ParkCard/CardModel.iv
					sconst_0;
					invokevirtual 50;		// ParkCard/CryptoManager.decrypt([BSS[BS[BS)V
					getfield_a_this 25;		// reference ParkCard/CardModel.tempDecryptBuffer
					sconst_0;
					baload;
					bspush 8;
					sshl;
					getfield_a_this 25;		// reference ParkCard/CardModel.tempDecryptBuffer
					sconst_1;
					baload;
					sspush 255;
					sand;
					sor;
					sstore 6;
				L6:	sload 5;
					ifle L8;
				L7:	sload 6;
					sload 5;
					sadd;
					sspush 30000;
					if_scmple L9;
				L8:	sspush 27012;
					invokestatic 162;		// javacard/framework/ISOException.throwIt(S)V
				L9:	sload 6;
					sload 5;
					sadd;
					sstore 7;
				L10:	getfield_a_this 25;		// reference ParkCard/CardModel.tempDecryptBuffer
					sconst_0;
					bspush 16;
					sconst_0;
					invokestatic 155;		// javacard/framework/Util.arrayFillNonAtomic([BSSB)S
					pop;
					getfield_a_this 25;		// reference ParkCard/CardModel.tempDecryptBuffer
					sconst_0;
					sload 7;
					bspush 8;
					sshr;
					s2b;
					bastore;
					getfield_a_this 25;		// reference ParkCard/CardModel.tempDecryptBuffer
					sconst_1;
					sload 7;
					s2b;
					bastore;
					aload_2;
					getfield_a_this 25;		// reference ParkCard/CardModel.tempDecryptBuffer
					sconst_0;
					bspush 16;
					getfield_a_this 7;		// reference ParkCard/CardModel.balance
					sconst_0;
					getfield_a_this 16;		// reference ParkCard/CardModel.iv
					sconst_0;
					invokevirtual 177;		// ParkCard/CryptoManager.encrypt([BSS[BS[BS)V
					return;
		}

		.method public checkBalance(Ljavacard/framework/APDU;LParkCard/CryptoManager;)V 32 {
			.stack 8;
			.locals 2;

			.descriptor	Ljavacard/framework/APDU;	2.10;

				L0:	aload_2;
					getfield_a_this 7;		// reference ParkCard/CardModel.balance
					sconst_0;
					bspush 16;
					getfield_a_this 25;		// reference ParkCard/CardModel.tempDecryptBuffer
					sconst_0;
					getfield_a_this 16;		// reference ParkCard/CardModel.iv
					sconst_0;
					invokevirtual 50;		// ParkCard/CryptoManager.decrypt([BSS[BS[BS)V
					getfield_a_this 25;		// reference ParkCard/CardModel.tempDecryptBuffer
					sconst_0;
					baload;
					bspush 8;
					sshl;
					getfield_a_this 25;		// reference ParkCard/CardModel.tempDecryptBuffer
					sconst_1;
					baload;
					sspush 255;
					sand;
					sor;
					sstore_3;
				L1:	aload_1;
					invokevirtual 174;		// javacard/framework/APDU.getBuffer()[B
					astore 4;
				L2:	aload 4;
					sconst_0;
					sload_3;
					bspush 8;
					sshr;
					s2b;
					bastore;
					aload 4;
					sconst_1;
					sload_3;
					s2b;
					bastore;
					aload_1;
					invokevirtual 51;		// javacard/framework/APDU.setOutgoing()S
					pop;
					aload_1;
					sconst_2;
					invokevirtual 52;		// javacard/framework/APDU.setOutgoingLength(S)V
					aload_1;
					sconst_0;
					sconst_2;
					invokevirtual 56;		// javacard/framework/APDU.sendBytes(SS)V
					return;
		}

		.method public makePayment(Ljavacard/framework/APDU;LParkCard/CryptoManager;)V 33 {
			.stack 8;
			.locals 5;

			.descriptor	Ljavacard/framework/APDU;	2.10;

				L0:	aload_1;
					invokevirtual 176;		// javacard/framework/APDU.setIncomingAndReceive()S
					sstore_3;
				L1:	sload_3;
					sconst_2;
					if_scmpeq L3;
				L2:	sspush 26368;
					invokestatic 162;		// javacard/framework/ISOException.throwIt(S)V
				L3:	aload_1;
					invokevirtual 174;		// javacard/framework/APDU.getBuffer()[B
					astore 4;
				L4:	aload 4;
					sconst_5;
					baload;
					bspush 8;
					sshl;
					aload 4;
					bspush 6;
					baload;
					sspush 255;
					sand;
					sor;
					sstore 5;
				L5:	aload_2;
					getfield_a_this 7;		// reference ParkCard/CardModel.balance
					sconst_0;
					bspush 16;
					getfield_a_this 25;		// reference ParkCard/CardModel.tempDecryptBuffer
					sconst_0;
					getfield_a_this 16;		// reference ParkCard/CardModel.iv
					sconst_0;
					invokevirtual 50;		// ParkCard/CryptoManager.decrypt([BSS[BS[BS)V
					getfield_a_this 25;		// reference ParkCard/CardModel.tempDecryptBuffer
					sconst_0;
					baload;
					bspush 8;
					sshl;
					getfield_a_this 25;		// reference ParkCard/CardModel.tempDecryptBuffer
					sconst_1;
					baload;
					sspush 255;
					sand;
					sor;
					sstore 6;
				L6:	sload 5;
					ifle L8;
				L7:	sload 6;
					sload 5;
					if_scmpge L12;
				L8:	sload 6;
					sload 5;
					if_scmpge L10;
				L9:	sspush 26881;
					goto L11;
				L10:	sspush 27012;
				L11:	invokestatic 162;		// javacard/framework/ISOException.throwIt(S)V
				L12:	sload 6;
					sload 5;
					ssub;
					sstore 7;
				L13:	getfield_a_this 25;		// reference ParkCard/CardModel.tempDecryptBuffer
					sconst_0;
					bspush 16;
					sconst_0;
					invokestatic 155;		// javacard/framework/Util.arrayFillNonAtomic([BSSB)S
					pop;
					getfield_a_this 25;		// reference ParkCard/CardModel.tempDecryptBuffer
					sconst_0;
					sload 7;
					bspush 8;
					sshr;
					s2b;
					bastore;
					getfield_a_this 25;		// reference ParkCard/CardModel.tempDecryptBuffer
					sconst_1;
					sload 7;
					s2b;
					bastore;
					aload_2;
					getfield_a_this 25;		// reference ParkCard/CardModel.tempDecryptBuffer
					sconst_0;
					bspush 16;
					getfield_a_this 7;		// reference ParkCard/CardModel.balance
					sconst_0;
					getfield_a_this 16;		// reference ParkCard/CardModel.iv
					sconst_0;
					invokevirtual 177;		// ParkCard/CryptoManager.encrypt([BSS[BS[BS)V
					return;
		}

		.method public reEncryptAllData(LParkCard/CryptoManager;LParkCard/CryptoManager;)V 34 {
			.stack 8;
			.locals 0;

				L0:	aload_1;
					getfield_a_this 4;		// reference ParkCard/CardModel.name
					sconst_0;
					bspush 64;
					getfield_a_this 25;		// reference ParkCard/CardModel.tempDecryptBuffer
					sconst_0;
					getfield_a_this 16;		// reference ParkCard/CardModel.iv
					sconst_0;
					invokevirtual 50;		// ParkCard/CryptoManager.decrypt([BSS[BS[BS)V
					aload_2;
					getfield_a_this 25;		// reference ParkCard/CardModel.tempDecryptBuffer
					sconst_0;
					bspush 64;
					getfield_a_this 4;		// reference ParkCard/CardModel.name
					sconst_0;
					getfield_a_this 16;		// reference ParkCard/CardModel.iv
					sconst_0;
					invokevirtual 177;		// ParkCard/CryptoManager.encrypt([BSS[BS[BS)V
					aload_1;
					getfield_a_this 5;		// reference ParkCard/CardModel.dateOfBirth
					sconst_0;
					bspush 16;
					getfield_a_this 25;		// reference ParkCard/CardModel.tempDecryptBuffer
					sconst_0;
					getfield_a_this 16;		// reference ParkCard/CardModel.iv
					sconst_0;
					invokevirtual 50;		// ParkCard/CryptoManager.decrypt([BSS[BS[BS)V
					aload_2;
					getfield_a_this 25;		// reference ParkCard/CardModel.tempDecryptBuffer
					sconst_0;
					bspush 16;
					getfield_a_this 5;		// reference ParkCard/CardModel.dateOfBirth
					sconst_0;
					getfield_a_this 16;		// reference ParkCard/CardModel.iv
					sconst_0;
					invokevirtual 177;		// ParkCard/CryptoManager.encrypt([BSS[BS[BS)V
					aload_1;
					getfield_a_this 6;		// reference ParkCard/CardModel.phoneNumber
					sconst_0;
					bspush 16;
					getfield_a_this 25;		// reference ParkCard/CardModel.tempDecryptBuffer
					sconst_0;
					getfield_a_this 16;		// reference ParkCard/CardModel.iv
					sconst_0;
					invokevirtual 50;		// ParkCard/CryptoManager.decrypt([BSS[BS[BS)V
					aload_2;
					getfield_a_this 25;		// reference ParkCard/CardModel.tempDecryptBuffer
					sconst_0;
					bspush 16;
					getfield_a_this 6;		// reference ParkCard/CardModel.phoneNumber
					sconst_0;
					getfield_a_this 16;		// reference ParkCard/CardModel.iv
					sconst_0;
					invokevirtual 177;		// ParkCard/CryptoManager.encrypt([BSS[BS[BS)V
					aload_1;
					getfield_a_this 7;		// reference ParkCard/CardModel.balance
					sconst_0;
					bspush 16;
					getfield_a_this 25;		// reference ParkCard/CardModel.tempDecryptBuffer
					sconst_0;
					getfield_a_this 16;		// reference ParkCard/CardModel.iv
					sconst_0;
					invokevirtual 50;		// ParkCard/CryptoManager.decrypt([BSS[BS[BS)V
					aload_2;
					getfield_a_this 25;		// reference ParkCard/CardModel.tempDecryptBuffer
					sconst_0;
					bspush 16;
					getfield_a_this 7;		// reference ParkCard/CardModel.balance
					sconst_0;
					getfield_a_this 16;		// reference ParkCard/CardModel.iv
					sconst_0;
					invokevirtual 177;		// ParkCard/CryptoManager.encrypt([BSS[BS[BS)V
					return;
		}

	}

	.class public CryptoManager 1 extends 0.0 {		// extends java/lang/Object

		.fields {
			private final 3.1 cbcCipher 0;		// Ljavacardx/crypto/Cipher;
			private final 3.1 ecbCipher 1;		// Ljavacardx/crypto/Cipher;
			private final byte[] aesKey 2;		// [B
			private final byte[] pinKey 3;		// [B
			private final byte[] derivedBuf 4;		// [B
			private final PBKDF2 pbkdf2 5;		// LParkCard/PBKDF2;
			private boolean keyReady 6;		// Z
			private static final short AES_KEY_SIZE = 16;		// S
		}

		.publicMethodTable 1 {
			equals(Ljava/lang/Object;)Z;
			deriveKeyFromPIN([BSB[BSSZ)V;
			deriveKeyFromPIN([BSB[BSS)V;
			wrapMasterKey([BS[BS[BS)V;
			unwrapMasterKey([BS[BS)V;
			wrapLoadedMasterKey([BS[BS)V;
			encrypt([BSS[BS[BS)V;
			decrypt([BSS[BS[BS)V;
			encryptPhotoECB([BSS[BS)V;
			decryptPhotoECB([BSS[BS)V;
			clearKey()V;
			isKeyReady()Z;
		}

		.packageMethodTable 0 {
		}

		.method public <init>()V 0 {
			.stack 3;
			.locals 0;

				L0:	aload_0;
					invokespecial 58;		// java/lang/Object.<init>()V
					aload_0;
					bspush 13;
					sconst_0;
					invokestatic 57;		// javacardx/crypto/Cipher.getInstance(BZ)Ljavacardx/crypto/Cipher;
					putfield_a 26;		// reference ParkCard/CryptoManager.cbcCipher
					aload_0;
					bspush 14;
					sconst_0;
					invokestatic 57;		// javacardx/crypto/Cipher.getInstance(BZ)Ljavacardx/crypto/Cipher;
					putfield_a 27;		// reference ParkCard/CryptoManager.ecbCipher
					aload_0;
					bspush 16;
					sconst_2;
					invokestatic 77;		// javacard/framework/JCSystem.makeTransientByteArray(SB)[B
					putfield_a 28;		// reference ParkCard/CryptoManager.aesKey
					aload_0;
					bspush 16;
					sconst_2;
					invokestatic 77;		// javacard/framework/JCSystem.makeTransientByteArray(SB)[B
					putfield_a 29;		// reference ParkCard/CryptoManager.pinKey
					aload_0;
					bspush 20;
					sconst_2;
					invokestatic 77;		// javacard/framework/JCSystem.makeTransientByteArray(SB)[B
					putfield_a 30;		// reference ParkCard/CryptoManager.derivedBuf
					aload_0;
					sconst_0;
					putfield_b 31;		// boolean ParkCard/CryptoManager.keyReady
					aload_0;
					new 64;		// ParkCard/PBKDF2
					dup;
					invokespecial 65;		// ParkCard/PBKDF2.<init>()V
					putfield_a 32;		// reference ParkCard/CryptoManager.pbkdf2
					return;
		}

		.method public deriveKeyFromPIN([BSB[BSSZ)V 1 {
			.stack 10;
			.locals 0;

				L0:	getfield_a_this 32;		// reference ParkCard/CryptoManager.pbkdf2
					aload_1;
					sload_2;
					sload_3;
					aload 4;
					sload 5;
					sload 6;
					sspush 200;
					getfield_a_this 30;		// reference ParkCard/CryptoManager.derivedBuf
					sconst_0;
					invokevirtual 67;		// ParkCard/PBKDF2.deriveKey([BSS[BSSS[BS)V
					getfield_a_this 30;		// reference ParkCard/CryptoManager.derivedBuf
					sconst_0;
					getfield_a_this 29;		// reference ParkCard/CryptoManager.pinKey
					sconst_0;
					bspush 16;
					invokestatic 163;		// javacard/framework/Util.arrayCopyNonAtomic([BS[BSS)S
					pop;
					sload 7;
					ifne L2;
				L1:	aload_0;
					sconst_0;
					putfield_b 31;		// boolean ParkCard/CryptoManager.keyReady
				L2:	return;
		}

		.method public deriveKeyFromPIN([BSB[BSS)V 2 {
			.stack 8;
			.locals 0;

				L0:	aload_0;
					aload_1;
					sload_2;
					sload_3;
					aload 4;
					sload 5;
					sload 6;
					sconst_0;
					invokevirtual 68;		// ParkCard/CryptoManager.deriveKeyFromPIN([BSB[BSSZ)V
					return;
		}

		.method public wrapMasterKey([BS[BS[BS)V 3 {
			.stack 6;
			.locals 1;

				L0:	bspush 15;
					sspush 128;
					sconst_0;
					invokestatic 69;		// javacard/security/KeyBuilder.buildKey(BSZ)Ljavacard/security/Key;
					checkcast 0 70;		// T_CLASSORINTERFACE javacard/security/AESKey
					astore 7;
				L1:	aload 7;
					getfield_a_this 29;		// reference ParkCard/CryptoManager.pinKey
					sconst_0;
					invokeinterface 3 70 4;		// javacard/security/AESKey
					getfield_a_this 26;		// reference ParkCard/CryptoManager.cbcCipher
					aload 7;
					sconst_2;
					aload 5;
					sload 6;
					bspush 16;
					invokevirtual 71;		// javacardx/crypto/Cipher.init(Ljavacard/security/Key;B[BSS)V
					getfield_a_this 26;		// reference ParkCard/CryptoManager.cbcCipher
					aload_1;
					sload_2;
					bspush 16;
					aload_3;
					sload 4;
					invokevirtual 72;		// javacardx/crypto/Cipher.doFinal([BSS[BS)S
					pop;
					return;
		}

		.method public unwrapMasterKey([BS[BS)V 4 {
			.stack 6;
			.locals 1;

				L0:	bspush 15;
					sspush 128;
					sconst_0;
					invokestatic 69;		// javacard/security/KeyBuilder.buildKey(BSZ)Ljavacard/security/Key;
					checkcast 0 70;		// T_CLASSORINTERFACE javacard/security/AESKey
					astore 5;
				L1:	aload 5;
					getfield_a_this 29;		// reference ParkCard/CryptoManager.pinKey
					sconst_0;
					invokeinterface 3 70 4;		// javacard/security/AESKey
					getfield_a_this 26;		// reference ParkCard/CryptoManager.cbcCipher
					aload 5;
					sconst_1;
					aload_3;
					sload 4;
					bspush 16;
					invokevirtual 71;		// javacardx/crypto/Cipher.init(Ljavacard/security/Key;B[BSS)V
					getfield_a_this 26;		// reference ParkCard/CryptoManager.cbcCipher
					aload_1;
					sload_2;
					bspush 16;
					getfield_a_this 28;		// reference ParkCard/CryptoManager.aesKey
					sconst_0;
					invokevirtual 72;		// javacardx/crypto/Cipher.doFinal([BSS[BS)S
					pop;
					aload_0;
					sconst_1;
					putfield_b 31;		// boolean ParkCard/CryptoManager.keyReady
					return;
		}

		.method public wrapLoadedMasterKey([BS[BS)V 5 {
			.stack 7;
			.locals 0;

				L0:	getfield_b_this 31;		// boolean ParkCard/CryptoManager.keyReady
					ifne L2;
				L1:	sspush 27013;
					invokestatic 162;		// javacard/framework/ISOException.throwIt(S)V
				L2:	aload_0;
					getfield_a_this 28;		// reference ParkCard/CryptoManager.aesKey
					sconst_0;
					aload_1;
					sload_2;
					aload_3;
					sload 4;
					invokevirtual 154;		// ParkCard/CryptoManager.wrapMasterKey([BS[BS[BS)V
					return;
		}

		.method public encrypt([BSS[BS[BS)V 6 {
			.stack 6;
			.locals 1;

				L0:	getfield_b_this 31;		// boolean ParkCard/CryptoManager.keyReady
					ifne L2;
				L1:	sspush 27013;
					invokestatic 162;		// javacard/framework/ISOException.throwIt(S)V
				L2:	sload_3;
					bspush 16;
					srem;
					ifeq L4;
				L3:	sspush 26368;
					invokestatic 162;		// javacard/framework/ISOException.throwIt(S)V
				L4:	bspush 15;
					sspush 128;
					sconst_0;
					invokestatic 69;		// javacard/security/KeyBuilder.buildKey(BSZ)Ljavacard/security/Key;
					checkcast 0 70;		// T_CLASSORINTERFACE javacard/security/AESKey
					astore 8;
				L5:	aload 8;
					getfield_a_this 28;		// reference ParkCard/CryptoManager.aesKey
					sconst_0;
					invokeinterface 3 70 4;		// javacard/security/AESKey
					getfield_a_this 26;		// reference ParkCard/CryptoManager.cbcCipher
					aload 8;
					sconst_2;
					aload 6;
					sload 7;
					bspush 16;
					invokevirtual 71;		// javacardx/crypto/Cipher.init(Ljavacard/security/Key;B[BSS)V
					getfield_a_this 26;		// reference ParkCard/CryptoManager.cbcCipher
					aload_1;
					sload_2;
					sload_3;
					aload 4;
					sload 5;
					invokevirtual 72;		// javacardx/crypto/Cipher.doFinal([BSS[BS)S
					pop;
					return;
		}

		.method public decrypt([BSS[BS[BS)V 7 {
			.stack 6;
			.locals 1;

				L0:	getfield_b_this 31;		// boolean ParkCard/CryptoManager.keyReady
					ifne L2;
				L1:	sspush 27013;
					invokestatic 162;		// javacard/framework/ISOException.throwIt(S)V
				L2:	sload_3;
					bspush 16;
					srem;
					ifeq L4;
				L3:	sspush 26368;
					invokestatic 162;		// javacard/framework/ISOException.throwIt(S)V
				L4:	bspush 15;
					sspush 128;
					sconst_0;
					invokestatic 69;		// javacard/security/KeyBuilder.buildKey(BSZ)Ljavacard/security/Key;
					checkcast 0 70;		// T_CLASSORINTERFACE javacard/security/AESKey
					astore 8;
				L5:	aload 8;
					getfield_a_this 28;		// reference ParkCard/CryptoManager.aesKey
					sconst_0;
					invokeinterface 3 70 4;		// javacard/security/AESKey
					getfield_a_this 26;		// reference ParkCard/CryptoManager.cbcCipher
					aload 8;
					sconst_1;
					aload 6;
					sload 7;
					bspush 16;
					invokevirtual 71;		// javacardx/crypto/Cipher.init(Ljavacard/security/Key;B[BSS)V
					getfield_a_this 26;		// reference ParkCard/CryptoManager.cbcCipher
					aload_1;
					sload_2;
					sload_3;
					aload 4;
					sload 5;
					invokevirtual 72;		// javacardx/crypto/Cipher.doFinal([BSS[BS)S
					pop;
					return;
		}

		.method public encryptPhotoECB([BSS[BS)V 8 {
			.stack 6;
			.locals 1;

				L0:	getfield_b_this 31;		// boolean ParkCard/CryptoManager.keyReady
					ifne L2;
				L1:	sspush 27013;
					invokestatic 162;		// javacard/framework/ISOException.throwIt(S)V
				L2:	sload_3;
					bspush 16;
					srem;
					ifeq L4;
				L3:	sspush 26368;
					invokestatic 162;		// javacard/framework/ISOException.throwIt(S)V
				L4:	bspush 15;
					sspush 128;
					sconst_0;
					invokestatic 69;		// javacard/security/KeyBuilder.buildKey(BSZ)Ljavacard/security/Key;
					checkcast 0 70;		// T_CLASSORINTERFACE javacard/security/AESKey
					astore 6;
				L5:	aload 6;
					getfield_a_this 28;		// reference ParkCard/CryptoManager.aesKey
					sconst_0;
					invokeinterface 3 70 4;		// javacard/security/AESKey
					getfield_a_this 27;		// reference ParkCard/CryptoManager.ecbCipher
					aload 6;
					sconst_2;
					invokevirtual 73;		// javacardx/crypto/Cipher.init(Ljavacard/security/Key;B)V
					getfield_a_this 27;		// reference ParkCard/CryptoManager.ecbCipher
					aload_1;
					sload_2;
					sload_3;
					aload 4;
					sload 5;
					invokevirtual 72;		// javacardx/crypto/Cipher.doFinal([BSS[BS)S
					pop;
					return;
		}

		.method public decryptPhotoECB([BSS[BS)V 9 {
			.stack 6;
			.locals 1;

				L0:	getfield_b_this 31;		// boolean ParkCard/CryptoManager.keyReady
					ifne L2;
				L1:	sspush 27013;
					invokestatic 162;		// javacard/framework/ISOException.throwIt(S)V
				L2:	sload_3;
					bspush 16;
					srem;
					ifeq L4;
				L3:	sspush 26368;
					invokestatic 162;		// javacard/framework/ISOException.throwIt(S)V
				L4:	bspush 15;
					sspush 128;
					sconst_0;
					invokestatic 69;		// javacard/security/KeyBuilder.buildKey(BSZ)Ljavacard/security/Key;
					checkcast 0 70;		// T_CLASSORINTERFACE javacard/security/AESKey
					astore 6;
				L5:	aload 6;
					getfield_a_this 28;		// reference ParkCard/CryptoManager.aesKey
					sconst_0;
					invokeinterface 3 70 4;		// javacard/security/AESKey
					getfield_a_this 27;		// reference ParkCard/CryptoManager.ecbCipher
					aload 6;
					sconst_1;
					invokevirtual 73;		// javacardx/crypto/Cipher.init(Ljavacard/security/Key;B)V
					getfield_a_this 27;		// reference ParkCard/CryptoManager.ecbCipher
					aload_1;
					sload_2;
					sload_3;
					aload 4;
					sload 5;
					invokevirtual 72;		// javacardx/crypto/Cipher.doFinal([BSS[BS)S
					pop;
					return;
		}

		.method public clearKey()V 10 {
			.stack 4;
			.locals 0;

				L0:	getfield_a_this 28;		// reference ParkCard/CryptoManager.aesKey
					sconst_0;
					bspush 16;
					sconst_0;
					invokestatic 155;		// javacard/framework/Util.arrayFillNonAtomic([BSSB)S
					pop;
					getfield_a_this 29;		// reference ParkCard/CryptoManager.pinKey
					sconst_0;
					bspush 16;
					sconst_0;
					invokestatic 155;		// javacard/framework/Util.arrayFillNonAtomic([BSSB)S
					pop;
					aload_0;
					sconst_0;
					putfield_b 31;		// boolean ParkCard/CryptoManager.keyReady
					return;
		}

		.method public isKeyReady()Z 11 {
			.stack 1;
			.locals 0;

				L0:	getfield_b_this 31;		// boolean ParkCard/CryptoManager.keyReady
					sreturn;
		}

	}

	.class public CustomerCardApplet 2 extends 2.3 {		// extends javacard/framework/Applet

		.fields {
			private CardModel model 0;		// LParkCard/CardModel;
			private PinManager pinMgr 1;		// LParkCard/PinManager;
			private GameManager gameMgr 2;		// LParkCard/GameManager;
			private CryptoManager cryptoMgr 3;		// LParkCard/CryptoManager;
			private static final byte INS_CREATE_PIN = 1;		// B
			private static final byte INS_VERIFY_PIN = 2;		// B
			private static final byte INS_CHANGE_PIN = 3;		// B
			private static final byte INS_GET_PIN_TRIES = 4;		// B
			private static final byte INS_RESET_PIN_COUNTER = 5;		// B
			private static final byte INS_RESET_WITH_PUK = 6;		// B
			private static final byte INS_WRITE_INFO = 7;		// B
			private static final byte INS_START_PHOTO_WRITE = 8;		// B
			private static final byte INS_WRITE_PHOTO_CHUNK = 9;		// B
			private static final byte INS_FINISH_PHOTO_WRITE = 10;		// B
			private static final byte INS_READ_INFO = 11;		// B
			private static final byte INS_READ_PHOTO_CHUNK = 12;		// B
			private static final byte INS_RECHARGE_BALANCE = 13;		// B
			private static final byte INS_CHECK_BALANCE = 14;		// B
			private static final byte INS_MAKE_PAYMENT = 15;		// B
			private static final byte INS_GET_CRYPTO_INFO = 16;		// B
			private static final byte INS_ADD_OR_INCREASE_TICKETS = 17;		// B
			private static final byte INS_DECREASE_GAME_TICKETS = 18;		// B
			private static final byte INS_READ_GAMES = 19;		// B
			private static final byte INS_UPDATE_GAME_TICKETS = 20;		// B
			private static final byte INS_FIND_GAME = 21;		// B
			private static final byte INS_REMOVE_GAME = 22;		// B
			private static final byte INS_SET_CUSTOMER_ID = 23;		// B
			private static final byte INS_GET_CUSTOMER_ID = 24;		// B
			private static final byte INS_SET_RSA_EXPONENT = 25;		// B
			private static final byte INS_SET_RSA_MODULUS = 26;		// B
			private static final byte INS_SIGN_CHALLENGE = 27;		// B
			private static final byte INS_GET_RSA_STATUS = 28;		// B
			private static final byte INS_GENERATE_RSA_KEYPAIR = 29;		// B
			private static final byte INS_GET_PUBLIC_KEY = 30;		// B
			private static final byte INS_VERIFY_ADMIN_PIN = 31;		// B
			private static final byte INS_CHANGE_ADMIN_PIN = 32;		// B
			private static final byte INS_RESET_USER_PIN = 33;		// B
			private static final byte INS_GET_ADMIN_PIN_TRIES = 34;		// B
			private static final short SW_SECURITY_STATUS_NOT_SATISFIED = 27010;		// S
			private static final short SW_AUTHENTICATION_METHOD_BLOCKED = 27011;		// S
			private static final short SW_INSUFFICIENT_BALANCE = 26881;		// S
			private static final short SW_RSA_NOT_READY = 27272;		// S
		}

		.publicMethodTable 4 {
			equals(Ljava/lang/Object;)Z;
			register()V;
			register([BSB)V;
			selectingApplet()Z;
			deselect()V;
			getShareableInterfaceObject(Ljavacard/framework/AID;B)Ljavacard/framework/Shareable;;
			select()Z;
			process(Ljavacard/framework/APDU;)V;
		}

		.packageMethodTable 0 {
		}

		.method private <init>()V {
			.stack 5;
			.locals 0;

				L0:	aload_0;
					invokespecial 74;		// javacard/framework/Applet.<init>()V
					aload_0;
					new 75;		// ParkCard/CardModel
					dup;
					invokespecial 76;		// ParkCard/CardModel.<init>()V
					putfield_a 33;		// reference ParkCard/CustomerCardApplet.model
					aload_0;
					new 78;		// ParkCard/PinManager
					dup;
					invokespecial 79;		// ParkCard/PinManager.<init>()V
					putfield_a 34;		// reference ParkCard/CustomerCardApplet.pinMgr
					aload_0;
					new 81;		// ParkCard/GameManager
					dup;
					getfield_a_this 33;		// reference ParkCard/CustomerCardApplet.model
					getfield_a 14;		// reference ParkCard/CardModel.gameList
					getfield_a_this 33;		// reference ParkCard/CustomerCardApplet.model
					getfield_a 15;		// reference ParkCard/CardModel.gameCountRef
					invokespecial 82;		// ParkCard/GameManager.<init>([B[S)V
					putfield_a 35;		// reference ParkCard/CustomerCardApplet.gameMgr
					aload_0;
					new 84;		// ParkCard/CryptoManager
					dup;
					invokespecial 85;		// ParkCard/CryptoManager.<init>()V
					putfield_a 36;		// reference ParkCard/CustomerCardApplet.cryptoMgr
					getfield_a_this 34;		// reference ParkCard/CustomerCardApplet.pinMgr
					getfield_a_this 36;		// reference ParkCard/CustomerCardApplet.cryptoMgr
					invokevirtual 87;		// ParkCard/PinManager.setCryptoManager(LParkCard/CryptoManager;)V
					getfield_a_this 34;		// reference ParkCard/CustomerCardApplet.pinMgr
					getfield_a_this 33;		// reference ParkCard/CustomerCardApplet.model
					invokevirtual 88;		// ParkCard/PinManager.setCardModel(LParkCard/CardModel;)V
					return;
		}

		.method public static install([BSB)V 0 {
			.stack 5;
			.locals 0;

				L0:	new 89;		// ParkCard/CustomerCardApplet
					dup;
					invokespecial 90;		// ParkCard/CustomerCardApplet.<init>()V
					aload_0;
					sload_1;
					sconst_1;
					sadd;
					aload_0;
					sload_1;
					baload;
					invokevirtual 91;		// javacard/framework/Applet.register([BSB)V
					return;
		}

		.method public process(Ljavacard/framework/APDU;)V 7 {
			.stack 3;
			.locals 2;

			.descriptor	Ljavacard/framework/APDU;	2.10;

				L0:	aload_0;
					invokevirtual 92;		// javacard/framework/Applet.selectingApplet()Z
					ifeq L2;
				L1:	return;
				L2:	aload_1;
					invokevirtual 174;		// javacard/framework/APDU.getBuffer()[B
					astore_2;
				L3:	aload_2;
					sconst_1;
					baload;
					sstore_3;
				L4:	sload_3;
					stableswitch L39 1 34 L5 L6 L7 L8 L9 L10 L12 L13 L14 L15 L16 L17 L18 L19 L20 L11 L21 L22 L23 L24 L25 L26 L27 L28 L29 L30 L31 L32 L33 L34 L35 L36 L37 L38;
				L5:	getfield_a_this 34;		// reference ParkCard/CustomerCardApplet.pinMgr
					aload_1;
					invokevirtual 93;		// ParkCard/PinManager.createPIN(Ljavacard/framework/APDU;)V
					goto_w L40;
				L6:	aload_0;
					aload_1;
					invokespecial 94;		// ParkCard/CustomerCardApplet.verifyPIN(Ljavacard/framework/APDU;)V
					goto_w L40;
				L7:	aload_0;
					aload_1;
					invokespecial 95;		// ParkCard/CustomerCardApplet.changePIN(Ljavacard/framework/APDU;)V
					goto_w L40;
				L8:	getfield_a_this 34;		// reference ParkCard/CustomerCardApplet.pinMgr
					aload_1;
					invokevirtual 96;		// ParkCard/PinManager.getPinTries(Ljavacard/framework/APDU;)V
					goto_w L40;
				L9:	getfield_a_this 34;		// reference ParkCard/CustomerCardApplet.pinMgr
					aload_1;
					invokevirtual 97;		// ParkCard/PinManager.resetPinCounter(Ljavacard/framework/APDU;)V
					goto_w L40;
				L10:	aload_0;
					aload_1;
					invokespecial 98;		// ParkCard/CustomerCardApplet.resetWithPUK(Ljavacard/framework/APDU;)V
					goto_w L40;
				L11:	aload_0;
					aload_1;
					invokespecial 99;		// ParkCard/CustomerCardApplet.getCryptoInfo(Ljavacard/framework/APDU;)V
					goto_w L40;
				L12:	aload_0;
					invokespecial 100;		// ParkCard/CustomerCardApplet.requireAuthenticated()V
					getfield_a_this 33;		// reference ParkCard/CustomerCardApplet.model
					aload_1;
					getfield_a_this 36;		// reference ParkCard/CustomerCardApplet.cryptoMgr
					invokevirtual 101;		// ParkCard/CardModel.writeCustomerInfo(Ljavacard/framework/APDU;LParkCard/CryptoManager;)V
					goto_w L40;
				L13:	aload_0;
					invokespecial 100;		// ParkCard/CustomerCardApplet.requireAuthenticated()V
					getfield_a_this 33;		// reference ParkCard/CustomerCardApplet.model
					invokevirtual 102;		// ParkCard/CardModel.startPhotoWrite()V
					goto_w L40;
				L14:	aload_0;
					invokespecial 100;		// ParkCard/CustomerCardApplet.requireAuthenticated()V
					getfield_a_this 33;		// reference ParkCard/CustomerCardApplet.model
					aload_1;
					invokevirtual 103;		// ParkCard/CardModel.writePhotoChunk(Ljavacard/framework/APDU;)V
					goto_w L40;
				L15:	aload_0;
					invokespecial 100;		// ParkCard/CustomerCardApplet.requireAuthenticated()V
					getfield_a_this 33;		// reference ParkCard/CustomerCardApplet.model
					aload_1;
					getfield_a_this 36;		// reference ParkCard/CustomerCardApplet.cryptoMgr
					invokevirtual 104;		// ParkCard/CardModel.finishPhotoWrite(Ljavacard/framework/APDU;LParkCard/CryptoManager;)V
					goto_w L40;
				L16:	aload_0;
					invokespecial 100;		// ParkCard/CustomerCardApplet.requireAuthenticated()V
					getfield_a_this 33;		// reference ParkCard/CustomerCardApplet.model
					aload_1;
					getfield_a_this 36;		// reference ParkCard/CustomerCardApplet.cryptoMgr
					invokevirtual 105;		// ParkCard/CardModel.readAllData(Ljavacard/framework/APDU;LParkCard/CryptoManager;)V
					goto_w L40;
				L17:	aload_0;
					invokespecial 100;		// ParkCard/CustomerCardApplet.requireAuthenticated()V
					getfield_a_this 33;		// reference ParkCard/CustomerCardApplet.model
					aload_1;
					getfield_a_this 36;		// reference ParkCard/CustomerCardApplet.cryptoMgr
					invokevirtual 106;		// ParkCard/CardModel.readPhotoChunk(Ljavacard/framework/APDU;LParkCard/CryptoManager;)V
					goto_w L40;
				L18:	aload_0;
					invokespecial 100;		// ParkCard/CustomerCardApplet.requireAuthenticated()V
					getfield_a_this 33;		// reference ParkCard/CustomerCardApplet.model
					aload_1;
					getfield_a_this 36;		// reference ParkCard/CustomerCardApplet.cryptoMgr
					invokevirtual 107;		// ParkCard/CardModel.rechargeBalance(Ljavacard/framework/APDU;LParkCard/CryptoManager;)V
					goto_w L40;
				L19:	aload_0;
					invokespecial 100;		// ParkCard/CustomerCardApplet.requireAuthenticated()V
					getfield_a_this 33;		// reference ParkCard/CustomerCardApplet.model
					aload_1;
					getfield_a_this 36;		// reference ParkCard/CustomerCardApplet.cryptoMgr
					invokevirtual 108;		// ParkCard/CardModel.checkBalance(Ljavacard/framework/APDU;LParkCard/CryptoManager;)V
					goto_w L40;
				L20:	aload_0;
					invokespecial 100;		// ParkCard/CustomerCardApplet.requireAuthenticated()V
					getfield_a_this 33;		// reference ParkCard/CustomerCardApplet.model
					aload_1;
					getfield_a_this 36;		// reference ParkCard/CustomerCardApplet.cryptoMgr
					invokevirtual 109;		// ParkCard/CardModel.makePayment(Ljavacard/framework/APDU;LParkCard/CryptoManager;)V
					goto_w L40;
				L21:	getfield_a_this 35;		// reference ParkCard/CustomerCardApplet.gameMgr
					aload_1;
					invokevirtual 110;		// ParkCard/GameManager.addOrIncreaseTickets(Ljavacard/framework/APDU;)V
					goto_w L40;
				L22:	getfield_a_this 35;		// reference ParkCard/CustomerCardApplet.gameMgr
					aload_1;
					invokevirtual 111;		// ParkCard/GameManager.decreaseGameTickets(Ljavacard/framework/APDU;)V
					goto_w L40;
				L23:	getfield_a_this 35;		// reference ParkCard/CustomerCardApplet.gameMgr
					aload_1;
					invokevirtual 112;		// ParkCard/GameManager.readGames(Ljavacard/framework/APDU;)V
					goto L40;
				L24:	getfield_a_this 35;		// reference ParkCard/CustomerCardApplet.gameMgr
					aload_1;
					invokevirtual 113;		// ParkCard/GameManager.updateGameTickets(Ljavacard/framework/APDU;)V
					goto L40;
				L25:	getfield_a_this 35;		// reference ParkCard/CustomerCardApplet.gameMgr
					aload_1;
					invokevirtual 114;		// ParkCard/GameManager.findGame(Ljavacard/framework/APDU;)V
					goto L40;
				L26:	getfield_a_this 35;		// reference ParkCard/CustomerCardApplet.gameMgr
					aload_1;
					invokevirtual 115;		// ParkCard/GameManager.removeGame(Ljavacard/framework/APDU;)V
					goto L40;
				L27:	aload_0;
					aload_1;
					invokespecial 116;		// ParkCard/CustomerCardApplet.setCustomerID(Ljavacard/framework/APDU;)V
					goto L40;
				L28:	aload_0;
					aload_1;
					invokespecial 117;		// ParkCard/CustomerCardApplet.getCustomerID(Ljavacard/framework/APDU;)V
					goto L40;
				L29:	aload_0;
					aload_1;
					invokespecial 118;		// ParkCard/CustomerCardApplet.setRSAExponent(Ljavacard/framework/APDU;)V
					goto L40;
				L30:	aload_0;
					aload_1;
					invokespecial 119;		// ParkCard/CustomerCardApplet.setRSAModulus(Ljavacard/framework/APDU;)V
					goto L40;
				L31:	aload_0;
					aload_1;
					invokespecial 120;		// ParkCard/CustomerCardApplet.signChallenge(Ljavacard/framework/APDU;)V
					goto L40;
				L32:	aload_0;
					aload_1;
					invokespecial 121;		// ParkCard/CustomerCardApplet.getRSAStatus(Ljavacard/framework/APDU;)V
					goto L40;
				L33:	aload_0;
					aload_1;
					invokespecial 122;		// ParkCard/CustomerCardApplet.generateRSAKeyPair(Ljavacard/framework/APDU;)V
					goto L40;
				L34:	aload_0;
					aload_1;
					invokespecial 123;		// ParkCard/CustomerCardApplet.getPublicKey(Ljavacard/framework/APDU;)V
					goto L40;
				L35:	aload_0;
					aload_1;
					invokespecial 124;		// ParkCard/CustomerCardApplet.verifyAdminPIN(Ljavacard/framework/APDU;)V
					goto L40;
				L36:	aload_0;
					aload_1;
					invokespecial 125;		// ParkCard/CustomerCardApplet.changeAdminPIN(Ljavacard/framework/APDU;)V
					goto L40;
				L37:	aload_0;
					aload_1;
					invokespecial 126;		// ParkCard/CustomerCardApplet.resetUserPIN(Ljavacard/framework/APDU;)V
					goto L40;
				L38:	getfield_a_this 34;		// reference ParkCard/CustomerCardApplet.pinMgr
					aload_1;
					invokevirtual 127;		// ParkCard/PinManager.getAdminPinTries(Ljavacard/framework/APDU;)V
					goto L40;
				L39:	sspush 27904;
					invokestatic 162;		// javacard/framework/ISOException.throwIt(S)V
				L40:	return;
		}

		.method private requireAuthenticated()V {
			.stack 1;
			.locals 0;

				L0:	getfield_a_this 33;		// reference ParkCard/CustomerCardApplet.model
					invokevirtual 128;		// ParkCard/CardModel.isDataReady()Z
					ifeq L2;
				L1:	getfield_a_this 36;		// reference ParkCard/CustomerCardApplet.cryptoMgr
					invokevirtual 160;		// ParkCard/CryptoManager.isKeyReady()Z
					ifne L3;
				L2:	sspush 27010;
					invokestatic 162;		// javacard/framework/ISOException.throwIt(S)V
				L3:	return;
		}

		.method private verifyPIN(Ljavacard/framework/APDU;)V {
			.stack 4;
			.locals 2;

			.descriptor	Ljavacard/framework/APDU;	2.10;

				L0:	aload_1;
					invokevirtual 174;		// javacard/framework/APDU.getBuffer()[B
					astore_2;
				L1:	aload_1;
					invokevirtual 176;		// javacard/framework/APDU.setIncomingAndReceive()S
					sstore_3;
				L2:	getfield_a_this 34;		// reference ParkCard/CustomerCardApplet.pinMgr
					aload_2;
					sconst_5;
					sload_3;
					s2b;
					invokevirtual 129;		// ParkCard/PinManager.verify([BSB)Z
					ifeq L5;
				L3:	getfield_a_this 33;		// reference ParkCard/CustomerCardApplet.model
					sconst_1;
					invokevirtual 130;		// ParkCard/CardModel.setDataReady(Z)V
					getfield_a_this 33;		// reference ParkCard/CustomerCardApplet.model
					invokevirtual 131;		// ParkCard/CardModel.isDataEncrypted()Z
					ifne L8;
				L4:	getfield_a_this 33;		// reference ParkCard/CustomerCardApplet.model
					getfield_a_this 36;		// reference ParkCard/CustomerCardApplet.cryptoMgr
					invokevirtual 132;		// ParkCard/CardModel.initializeBalance(LParkCard/CryptoManager;)V
					goto L8;
				L5:	getfield_a_this 33;		// reference ParkCard/CustomerCardApplet.model
					sconst_0;
					invokevirtual 130;		// ParkCard/CardModel.setDataReady(Z)V
					getfield_a_this 36;		// reference ParkCard/CustomerCardApplet.cryptoMgr
					invokevirtual 133;		// ParkCard/CryptoManager.clearKey()V
					getfield_a_this 34;		// reference ParkCard/CustomerCardApplet.pinMgr
					invokevirtual 134;		// ParkCard/PinManager.getTriesRemaining()B
					ifne L7;
				L6:	sspush 27011;
					invokestatic 162;		// javacard/framework/ISOException.throwIt(S)V
					goto L8;
				L7:	sspush 27264;
					invokestatic 162;		// javacard/framework/ISOException.throwIt(S)V
				L8:	return;
		}

		.method private changePIN(Ljavacard/framework/APDU;)V {
			.stack 2;
			.locals 0;

			.descriptor	Ljavacard/framework/APDU;	2.10;

				L0:	getfield_a_this 34;		// reference ParkCard/CustomerCardApplet.pinMgr
					invokevirtual 135;		// ParkCard/PinManager.isPINValidated()Z
					ifne L2;
				L1:	sspush 27013;
					invokestatic 162;		// javacard/framework/ISOException.throwIt(S)V
				L2:	getfield_a_this 34;		// reference ParkCard/CustomerCardApplet.pinMgr
					aload_1;
					invokevirtual 136;		// ParkCard/PinManager.changePIN(Ljavacard/framework/APDU;)V
					return;
		}

		.method private resetWithPUK(Ljavacard/framework/APDU;)V {
			.stack 2;
			.locals 0;

			.descriptor	Ljavacard/framework/APDU;	2.10;

				L0:	getfield_a_this 34;		// reference ParkCard/CustomerCardApplet.pinMgr
					aload_1;
					invokevirtual 137;		// ParkCard/PinManager.resetWithPUK(Ljavacard/framework/APDU;)V
					getfield_a_this 33;		// reference ParkCard/CustomerCardApplet.model
					sconst_0;
					invokevirtual 130;		// ParkCard/CardModel.setDataReady(Z)V
					getfield_a_this 36;		// reference ParkCard/CustomerCardApplet.cryptoMgr
					invokevirtual 133;		// ParkCard/CryptoManager.clearKey()V
					return;
		}

		.method private getCryptoInfo(Ljavacard/framework/APDU;)V {
			.stack 5;
			.locals 3;

			.descriptor	Ljavacard/framework/APDU;	2.10;

				L0:	aload_1;
					invokevirtual 174;		// javacard/framework/APDU.getBuffer()[B
					astore_2;
				L1:	getfield_a_this 33;		// reference ParkCard/CustomerCardApplet.model
					invokevirtual 138;		// ParkCard/CardModel.getIV()[B
					astore_3;
				L2:	getfield_a_this 33;		// reference ParkCard/CustomerCardApplet.model
					invokevirtual 139;		// ParkCard/CardModel.getSalt()[B
					astore 4;
				L3:	aload_3;
					sconst_0;
					aload_2;
					sconst_0;
					bspush 16;
					invokestatic 163;		// javacard/framework/Util.arrayCopyNonAtomic([BS[BSS)S
					pop;
					aload 4;
					sconst_0;
					aload_2;
					bspush 16;
					bspush 16;
					invokestatic 163;		// javacard/framework/Util.arrayCopyNonAtomic([BS[BSS)S
					pop;
					aload_1;
					invokevirtual 51;		// javacard/framework/APDU.setOutgoing()S
					pop;
					aload_1;
					bspush 32;
					invokevirtual 52;		// javacard/framework/APDU.setOutgoingLength(S)V
					aload_1;
					aload_2;
					sconst_0;
					bspush 32;
					invokevirtual 53;		// javacard/framework/APDU.sendBytesLong([BSS)V
					return;
		}

		.method private setCustomerID(Ljavacard/framework/APDU;)V {
			.stack 4;
			.locals 2;

			.descriptor	Ljavacard/framework/APDU;	2.10;

				L0:	aload_1;
					invokevirtual 174;		// javacard/framework/APDU.getBuffer()[B
					astore_2;
				L1:	aload_1;
					invokevirtual 176;		// javacard/framework/APDU.setIncomingAndReceive()S
					sstore_3;
				L2:	sload_3;
					bspush 15;
					if_scmple L4;
				L3:	sspush 26368;
					invokestatic 162;		// javacard/framework/ISOException.throwIt(S)V
				L4:	getfield_a_this 33;		// reference ParkCard/CustomerCardApplet.model
					aload_2;
					sconst_5;
					sload_3;
					s2b;
					invokevirtual 140;		// ParkCard/CardModel.setCustomerID([BSS)V
					aload_1;
					invokevirtual 51;		// javacard/framework/APDU.setOutgoing()S
					pop;
					aload_1;
					sconst_0;
					invokevirtual 52;		// javacard/framework/APDU.setOutgoingLength(S)V
					return;
		}

		.method private getCustomerID(Ljavacard/framework/APDU;)V {
			.stack 4;
			.locals 1;

			.descriptor	Ljavacard/framework/APDU;	2.10;

				L0:	aload_1;
					invokevirtual 174;		// javacard/framework/APDU.getBuffer()[B
					astore_2;
				L1:	getfield_a_this 33;		// reference ParkCard/CustomerCardApplet.model
					aload_2;
					sconst_0;
					invokevirtual 141;		// ParkCard/CardModel.getCustomerID([BS)V
					aload_1;
					invokevirtual 51;		// javacard/framework/APDU.setOutgoing()S
					pop;
					aload_1;
					bspush 15;
					invokevirtual 52;		// javacard/framework/APDU.setOutgoingLength(S)V
					aload_1;
					aload_2;
					sconst_0;
					bspush 15;
					invokevirtual 53;		// javacard/framework/APDU.sendBytesLong([BSS)V
					return;
		}

		.method private setRSAExponent(Ljavacard/framework/APDU;)V {
			.stack 4;
			.locals 2;

			.descriptor	Ljavacard/framework/APDU;	2.10;

				L0:	aload_1;
					invokevirtual 174;		// javacard/framework/APDU.getBuffer()[B
					astore_2;
				L1:	aload_1;
					invokevirtual 176;		// javacard/framework/APDU.setIncomingAndReceive()S
					sstore_3;
				L2:	sload_3;
					sspush 128;
					if_scmpeq L4;
				L3:	sspush 26368;
					invokestatic 162;		// javacard/framework/ISOException.throwIt(S)V
				L4:	getfield_a_this 33;		// reference ParkCard/CustomerCardApplet.model
					aload_2;
					sconst_5;
					sload_3;
					invokevirtual 142;		// ParkCard/CardModel.setRSAExponent([BSS)V
					aload_1;
					invokevirtual 51;		// javacard/framework/APDU.setOutgoing()S
					pop;
					aload_1;
					sconst_0;
					invokevirtual 52;		// javacard/framework/APDU.setOutgoingLength(S)V
					return;
		}

		.method private setRSAModulus(Ljavacard/framework/APDU;)V {
			.stack 4;
			.locals 2;

			.descriptor	Ljavacard/framework/APDU;	2.10;

				L0:	aload_1;
					invokevirtual 174;		// javacard/framework/APDU.getBuffer()[B
					astore_2;
				L1:	aload_1;
					invokevirtual 176;		// javacard/framework/APDU.setIncomingAndReceive()S
					sstore_3;
				L2:	sload_3;
					sspush 128;
					if_scmpeq L4;
				L3:	sspush 26368;
					invokestatic 162;		// javacard/framework/ISOException.throwIt(S)V
				L4:	getfield_a_this 33;		// reference ParkCard/CustomerCardApplet.model
					aload_2;
					sconst_5;
					sload_3;
					invokevirtual 143;		// ParkCard/CardModel.setRSAModulus([BSS)V
					aload_1;
					invokevirtual 51;		// javacard/framework/APDU.setOutgoing()S
					pop;
					aload_1;
					sconst_0;
					invokevirtual 52;		// javacard/framework/APDU.setOutgoingLength(S)V
					return;
		}

		.method private signChallenge(Ljavacard/framework/APDU;)V {
			.stack 6;
			.locals 3;

			.descriptor	Ljavacard/framework/APDU;	2.10;

				L0:	getfield_a_this 33;		// reference ParkCard/CustomerCardApplet.model
					invokevirtual 144;		// ParkCard/CardModel.isRSAKeyReady()Z
					ifne L2;
				L1:	sspush 27272;
					invokestatic 162;		// javacard/framework/ISOException.throwIt(S)V
				L2:	aload_1;
					invokevirtual 174;		// javacard/framework/APDU.getBuffer()[B
					astore_2;
				L3:	aload_1;
					invokevirtual 176;		// javacard/framework/APDU.setIncomingAndReceive()S
					sstore_3;
				L4:	sload_3;
					bspush 32;
					if_scmpeq L6;
				L5:	sspush 26368;
					invokestatic 162;		// javacard/framework/ISOException.throwIt(S)V
				L6:	getfield_a_this 33;		// reference ParkCard/CustomerCardApplet.model
					aload_2;
					sconst_5;
					bspush 32;
					aload_2;
					sconst_0;
					invokevirtual 145;		// ParkCard/CardModel.signChallenge([BSS[BS)S
					sstore 4;
				L7:	aload_1;
					invokevirtual 51;		// javacard/framework/APDU.setOutgoing()S
					pop;
					aload_1;
					sload 4;
					invokevirtual 52;		// javacard/framework/APDU.setOutgoingLength(S)V
					aload_1;
					aload_2;
					sconst_0;
					sload 4;
					invokevirtual 53;		// javacard/framework/APDU.sendBytesLong([BSS)V
					return;
		}

		.method private getRSAStatus(Ljavacard/framework/APDU;)V {
			.stack 3;
			.locals 1;

			.descriptor	Ljavacard/framework/APDU;	2.10;

				L0:	aload_1;
					invokevirtual 174;		// javacard/framework/APDU.getBuffer()[B
					astore_2;
				L1:	aload_2;
					sconst_0;
					getfield_a_this 33;		// reference ParkCard/CustomerCardApplet.model
					invokevirtual 144;		// ParkCard/CardModel.isRSAKeyReady()Z
					ifeq L3;
				L2:	sconst_1;
					goto L4;
				L3:	sconst_0;
				L4:	bastore;
					aload_1;
					invokevirtual 51;		// javacard/framework/APDU.setOutgoing()S
					pop;
					aload_1;
					sconst_1;
					invokevirtual 52;		// javacard/framework/APDU.setOutgoingLength(S)V
					aload_1;
					sconst_0;
					sconst_1;
					invokevirtual 56;		// javacard/framework/APDU.sendBytes(SS)V
					return;
		}

		.method private generateRSAKeyPair(Ljavacard/framework/APDU;)V {
			.stack 1;
			.locals 0;

			.descriptor	Ljavacard/framework/APDU;	2.10;

				L0:	getfield_a_this 33;		// reference ParkCard/CustomerCardApplet.model
					invokevirtual 146;		// ParkCard/CardModel.generateRSAKeyPair()V
					return;
		}

		.method private getPublicKey(Ljavacard/framework/APDU;)V {
			.stack 4;
			.locals 4;

			.descriptor	Ljavacard/framework/APDU;	2.10;

				L0:	aload_1;
					invokevirtual 174;		// javacard/framework/APDU.getBuffer()[B
					astore_2;
				L1:	aload_1;
					invokevirtual 176;		// javacard/framework/APDU.setIncomingAndReceive()S
					sstore_3;
				L2:	sload_3;
					sconst_1;
					if_scmpeq L4;
				L3:	sspush 26368;
					invokestatic 162;		// javacard/framework/ISOException.throwIt(S)V
				L4:	aload_2;
					sconst_5;
					baload;
					sstore 4;
				L5:	sconst_0;
					sstore 5;
				L6:	sload 4;
					ifne L8;
				L7:	getfield_a_this 33;		// reference ParkCard/CustomerCardApplet.model
					aload_2;
					sconst_0;
					invokevirtual 147;		// ParkCard/CardModel.getPublicKeyModulus([BS)S
					sstore 5;
					goto L11;
				L8:	sload 4;
					sconst_1;
					if_scmpne L10;
				L9:	getfield_a_this 33;		// reference ParkCard/CustomerCardApplet.model
					aload_2;
					sconst_0;
					invokevirtual 148;		// ParkCard/CardModel.getPublicKeyExponent([BS)S
					sstore 5;
					goto L11;
				L10:	sspush 27270;
					invokestatic 162;		// javacard/framework/ISOException.throwIt(S)V
				L11:	aload_1;
					invokevirtual 51;		// javacard/framework/APDU.setOutgoing()S
					pop;
					aload_1;
					sload 5;
					invokevirtual 52;		// javacard/framework/APDU.setOutgoingLength(S)V
					aload_1;
					aload_2;
					sconst_0;
					sload 5;
					invokevirtual 53;		// javacard/framework/APDU.sendBytesLong([BSS)V
					return;
		}

		.method private verifyAdminPIN(Ljavacard/framework/APDU;)V {
			.stack 4;
			.locals 2;

			.descriptor	Ljavacard/framework/APDU;	2.10;

				L0:	aload_1;
					invokevirtual 174;		// javacard/framework/APDU.getBuffer()[B
					astore_2;
				L1:	aload_1;
					invokevirtual 176;		// javacard/framework/APDU.setIncomingAndReceive()S
					sstore_3;
				L2:	getfield_a_this 34;		// reference ParkCard/CustomerCardApplet.pinMgr
					aload_2;
					sconst_5;
					sload_3;
					s2b;
					invokevirtual 149;		// ParkCard/PinManager.verifyAdmin([BSB)Z
					ifeq L5;
				L3:	getfield_a_this 33;		// reference ParkCard/CustomerCardApplet.model
					sconst_1;
					invokevirtual 130;		// ParkCard/CardModel.setDataReady(Z)V
					getfield_a_this 33;		// reference ParkCard/CustomerCardApplet.model
					invokevirtual 131;		// ParkCard/CardModel.isDataEncrypted()Z
					ifne L8;
				L4:	getfield_a_this 33;		// reference ParkCard/CustomerCardApplet.model
					getfield_a_this 36;		// reference ParkCard/CustomerCardApplet.cryptoMgr
					invokevirtual 132;		// ParkCard/CardModel.initializeBalance(LParkCard/CryptoManager;)V
					goto L8;
				L5:	getfield_a_this 33;		// reference ParkCard/CustomerCardApplet.model
					sconst_0;
					invokevirtual 130;		// ParkCard/CardModel.setDataReady(Z)V
					getfield_a_this 36;		// reference ParkCard/CustomerCardApplet.cryptoMgr
					invokevirtual 133;		// ParkCard/CryptoManager.clearKey()V
					getfield_a_this 34;		// reference ParkCard/CustomerCardApplet.pinMgr
					invokevirtual 150;		// ParkCard/PinManager.getAdminTriesRemaining()B
					ifne L7;
				L6:	sspush 27011;
					invokestatic 162;		// javacard/framework/ISOException.throwIt(S)V
					goto L8;
				L7:	sspush 27264;
					invokestatic 162;		// javacard/framework/ISOException.throwIt(S)V
				L8:	return;
		}

		.method private changeAdminPIN(Ljavacard/framework/APDU;)V {
			.stack 2;
			.locals 0;

			.descriptor	Ljavacard/framework/APDU;	2.10;

				L0:	getfield_a_this 34;		// reference ParkCard/CustomerCardApplet.pinMgr
					invokevirtual 151;		// ParkCard/PinManager.isAdminPINValidated()Z
					ifne L2;
				L1:	sspush 27013;
					invokestatic 162;		// javacard/framework/ISOException.throwIt(S)V
				L2:	getfield_a_this 34;		// reference ParkCard/CustomerCardApplet.pinMgr
					aload_1;
					invokevirtual 152;		// ParkCard/PinManager.changeAdminPIN(Ljavacard/framework/APDU;)V
					return;
		}

		.method private resetUserPIN(Ljavacard/framework/APDU;)V {
			.stack 2;
			.locals 0;

			.descriptor	Ljavacard/framework/APDU;	2.10;

				L0:	getfield_a_this 34;		// reference ParkCard/CustomerCardApplet.pinMgr
					invokevirtual 151;		// ParkCard/PinManager.isAdminPINValidated()Z
					ifne L2;
				L1:	sspush 27013;
					invokestatic 162;		// javacard/framework/ISOException.throwIt(S)V
				L2:	getfield_a_this 34;		// reference ParkCard/CustomerCardApplet.pinMgr
					aload_1;
					invokevirtual 153;		// ParkCard/PinManager.resetUserPIN(Ljavacard/framework/APDU;)V
					return;
		}

		.method public deselect()V 4 {
			.stack 2;
			.locals 0;

				L0:	getfield_a_this 33;		// reference ParkCard/CustomerCardApplet.model
					invokevirtual 128;		// ParkCard/CardModel.isDataReady()Z
					ifeq L2;
				L1:	getfield_a_this 36;		// reference ParkCard/CustomerCardApplet.cryptoMgr
					invokevirtual 133;		// ParkCard/CryptoManager.clearKey()V
					getfield_a_this 33;		// reference ParkCard/CustomerCardApplet.model
					sconst_0;
					invokevirtual 130;		// ParkCard/CardModel.setDataReady(Z)V
				L2:	return;
		}

	}

	.class public GameManager 3 extends 0.0 {		// extends java/lang/Object

		.fields {
			private byte[] gameList 0;		// [B
			private short[] gameCountRef 1;		// [S
			private static final short MAX_GAMES = 50;		// S
			private static final short GAME_ENTRY_SIZE = 3;		// S
		}

		.publicMethodTable 1 {
			equals(Ljava/lang/Object;)Z;
			addOrIncreaseTickets(Ljavacard/framework/APDU;)V;
			decreaseGameTickets(Ljavacard/framework/APDU;)V;
			readGames(Ljavacard/framework/APDU;)V;
			updateGameTickets(Ljavacard/framework/APDU;)V;
			findGame(Ljavacard/framework/APDU;)V;
			removeGame(Ljavacard/framework/APDU;)V;
		}

		.packageMethodTable 0 {
		}

		.method public <init>([B[S)V 0 {
			.stack 2;
			.locals 0;

				L0:	aload_0;
					invokespecial 58;		// java/lang/Object.<init>()V
					aload_0;
					aload_1;
					putfield_a 37;		// reference ParkCard/GameManager.gameList
					aload_0;
					aload_2;
					putfield_a 38;		// reference ParkCard/GameManager.gameCountRef
					return;
		}

		.method private getGameCount()S {
			.stack 2;
			.locals 0;

				L0:	getfield_a_this 38;		// reference ParkCard/GameManager.gameCountRef
					sconst_0;
					saload;
					sreturn;
		}

		.method private setGameCount(S)V {
			.stack 3;
			.locals 0;

				L0:	getfield_a_this 38;		// reference ParkCard/GameManager.gameCountRef
					sconst_0;
					sload_1;
					sastore;
					return;
		}

		.method private findGameIndex(S)S {
			.stack 4;
			.locals 3;

				L0:	sconst_0;
					sstore_2;
				L1:	sload_2;
					aload_0;
					invokespecial 156;		// ParkCard/GameManager.getGameCount()S
					if_scmpge L7;
				L2:	sload_2;
					sconst_3;
					smul;
					sstore_3;
				L3:	getfield_a_this 37;		// reference ParkCard/GameManager.gameList
					sload_3;
					sconst_1;
					sadd;
					baload;
					bspush 8;
					sshl;
					getfield_a_this 37;		// reference ParkCard/GameManager.gameList
					sload_3;
					sconst_2;
					sadd;
					baload;
					sspush 255;
					sand;
					sor;
					sstore 4;
				L4:	sload 4;
					sload_1;
					if_scmpne L6;
				L5:	sload_2;
					sreturn;
				L6:	sinc 2 1;
					goto L1;
				L7:	sconst_m1;
					sreturn;
		}

		.method public addOrIncreaseTickets(Ljavacard/framework/APDU;)V 1 {
			.stack 4;
			.locals 7;

			.descriptor	Ljavacard/framework/APDU;	2.10;

				L0:	aload_1;
					invokevirtual 176;		// javacard/framework/APDU.setIncomingAndReceive()S
					sstore_2;
				L1:	sload_2;
					sconst_3;
					if_scmpeq L3;
				L2:	sspush 26368;
					invokestatic 162;		// javacard/framework/ISOException.throwIt(S)V
				L3:	aload_1;
					invokevirtual 174;		// javacard/framework/APDU.getBuffer()[B
					astore_3;
				L4:	aload_3;
					sconst_5;
					baload;
					sstore 4;
				L5:	aload_3;
					bspush 6;
					baload;
					bspush 8;
					sshl;
					aload_3;
					bspush 7;
					baload;
					sspush 255;
					sand;
					sor;
					sstore 5;
				L6:	sload 4;
					ifgt L8;
				L7:	sspush 27264;
					invokestatic 162;		// javacard/framework/ISOException.throwIt(S)V
				L8:	aload_0;
					sload 5;
					invokespecial 157;		// ParkCard/GameManager.findGameIndex(S)S
					sstore 6;
				L9:	sload 6;
					sconst_m1;
					if_scmpne L15;
				L10:	aload_0;
					invokespecial 156;		// ParkCard/GameManager.getGameCount()S
					bspush 50;
					if_scmplt L12;
				L11:	sspush 27268;
					invokestatic 162;		// javacard/framework/ISOException.throwIt(S)V
				L12:	aload_0;
					invokespecial 156;		// ParkCard/GameManager.getGameCount()S
					sconst_3;
					smul;
					sstore 7;
				L13:	getfield_a_this 37;		// reference ParkCard/GameManager.gameList
					sload 7;
					sload 4;
					bastore;
					getfield_a_this 37;		// reference ParkCard/GameManager.gameList
					sload 7;
					sconst_1;
					sadd;
					aload_3;
					bspush 6;
					baload;
					bastore;
					getfield_a_this 37;		// reference ParkCard/GameManager.gameList
					sload 7;
					sconst_2;
					sadd;
					aload_3;
					bspush 7;
					baload;
					bastore;
					aload_0;
					aload_0;
					invokespecial 156;		// ParkCard/GameManager.getGameCount()S
					sconst_1;
					sadd;
					invokespecial 158;		// ParkCard/GameManager.setGameCount(S)V
				L14:	goto L20;
				L15:	sload 6;
					sconst_3;
					smul;
					sstore 7;
				L16:	getfield_a_this 37;		// reference ParkCard/GameManager.gameList
					sload 7;
					baload;
					sstore 8;
				L17:	sload 8;
					sload 4;
					sadd;
					sspush 255;
					if_scmple L19;
				L18:	sspush 27012;
					invokestatic 162;		// javacard/framework/ISOException.throwIt(S)V
				L19:	getfield_a_this 37;		// reference ParkCard/GameManager.gameList
					sload 7;
					sload 8;
					sload 4;
					sadd;
					s2b;
					bastore;
				L20:	return;
		}

		.method public decreaseGameTickets(Ljavacard/framework/APDU;)V 2 {
			.stack 4;
			.locals 5;

			.descriptor	Ljavacard/framework/APDU;	2.10;

				L0:	aload_1;
					invokevirtual 176;		// javacard/framework/APDU.setIncomingAndReceive()S
					sstore_2;
				L1:	sload_2;
					sconst_3;
					if_scmpeq L3;
				L2:	sspush 26368;
					invokestatic 162;		// javacard/framework/ISOException.throwIt(S)V
				L3:	aload_1;
					invokevirtual 174;		// javacard/framework/APDU.getBuffer()[B
					astore_3;
				L4:	aload_3;
					sconst_5;
					baload;
					bspush 8;
					sshl;
					aload_3;
					bspush 6;
					baload;
					sspush 255;
					sand;
					sor;
					sstore 4;
				L5:	aload_3;
					bspush 7;
					baload;
					sstore 5;
				L6:	aload_0;
					sload 4;
					invokespecial 157;		// ParkCard/GameManager.findGameIndex(S)S
					sstore 6;
				L7:	sload 6;
					sconst_m1;
					if_scmpeq L10;
				L8:	sload 5;
					ifle L10;
				L9:	getfield_a_this 37;		// reference ParkCard/GameManager.gameList
					sload 6;
					sconst_3;
					smul;
					baload;
					sload 5;
					if_scmpge L11;
				L10:	sspush 27266;
					invokestatic 162;		// javacard/framework/ISOException.throwIt(S)V
				L11:	getfield_a_this 37;		// reference ParkCard/GameManager.gameList
					sload 6;
					sconst_3;
					smul;
					dup2;
					baload;
					sload 5;
					ssub;
					s2b;
					bastore;
					return;
		}

		.method public readGames(Ljavacard/framework/APDU;)V 3 {
			.stack 5;
			.locals 3;

			.descriptor	Ljavacard/framework/APDU;	2.10;

				L0:	aload_1;
					invokevirtual 174;		// javacard/framework/APDU.getBuffer()[B
					astore_2;
				L1:	aload_0;
					invokespecial 156;		// ParkCard/GameManager.getGameCount()S
					sstore_3;
				L2:	aload_2;
					sconst_0;
					sload_3;
					bspush 8;
					sshr;
					s2b;
					bastore;
					aload_2;
					sconst_1;
					sload_3;
					s2b;
					bastore;
					sload_3;
					sconst_3;
					smul;
					sstore 4;
				L3:	sload 4;
					ifle L5;
				L4:	getfield_a_this 37;		// reference ParkCard/GameManager.gameList
					sconst_0;
					aload_2;
					sconst_2;
					sload 4;
					invokestatic 163;		// javacard/framework/Util.arrayCopyNonAtomic([BS[BSS)S
					pop;
				L5:	aload_1;
					invokevirtual 51;		// javacard/framework/APDU.setOutgoing()S
					pop;
					aload_1;
					sconst_2;
					sload 4;
					sadd;
					invokevirtual 52;		// javacard/framework/APDU.setOutgoingLength(S)V
					aload_1;
					aload_2;
					sconst_0;
					sconst_2;
					sload 4;
					sadd;
					invokevirtual 53;		// javacard/framework/APDU.sendBytesLong([BSS)V
					return;
		}

		.method public updateGameTickets(Ljavacard/framework/APDU;)V 4 {
			.stack 3;
			.locals 5;

			.descriptor	Ljavacard/framework/APDU;	2.10;

				L0:	aload_1;
					invokevirtual 176;		// javacard/framework/APDU.setIncomingAndReceive()S
					sstore_2;
				L1:	sload_2;
					sconst_3;
					if_scmpeq L3;
				L2:	sspush 26368;
					invokestatic 162;		// javacard/framework/ISOException.throwIt(S)V
				L3:	aload_1;
					invokevirtual 174;		// javacard/framework/APDU.getBuffer()[B
					astore_3;
				L4:	aload_3;
					sconst_5;
					baload;
					bspush 8;
					sshl;
					aload_3;
					bspush 6;
					baload;
					sspush 255;
					sand;
					sor;
					sstore 4;
				L5:	aload_3;
					bspush 7;
					baload;
					sstore 5;
				L6:	aload_0;
					sload 4;
					invokespecial 157;		// ParkCard/GameManager.findGameIndex(S)S
					sstore 6;
				L7:	sload 6;
					sconst_m1;
					if_scmpne L9;
				L8:	sspush 27266;
					invokestatic 162;		// javacard/framework/ISOException.throwIt(S)V
				L9:	getfield_a_this 37;		// reference ParkCard/GameManager.gameList
					sload 6;
					sconst_3;
					smul;
					sload 5;
					bastore;
					return;
		}

		.method public findGame(Ljavacard/framework/APDU;)V 5 {
			.stack 5;
			.locals 5;

			.descriptor	Ljavacard/framework/APDU;	2.10;

				L0:	aload_1;
					invokevirtual 176;		// javacard/framework/APDU.setIncomingAndReceive()S
					sstore_2;
				L1:	sload_2;
					sconst_2;
					if_scmpeq L3;
				L2:	sspush 26368;
					invokestatic 162;		// javacard/framework/ISOException.throwIt(S)V
				L3:	aload_1;
					invokevirtual 174;		// javacard/framework/APDU.getBuffer()[B
					astore_3;
				L4:	aload_3;
					sconst_5;
					baload;
					bspush 8;
					sshl;
					aload_3;
					bspush 6;
					baload;
					sspush 255;
					sand;
					sor;
					sstore 4;
				L5:	aload_0;
					sload 4;
					invokespecial 157;		// ParkCard/GameManager.findGameIndex(S)S
					sstore 5;
				L6:	sload 5;
					sconst_m1;
					if_scmpne L8;
				L7:	aload_3;
					sconst_0;
					sconst_0;
					bastore;
					aload_1;
					invokevirtual 51;		// javacard/framework/APDU.setOutgoing()S
					pop;
					aload_1;
					sconst_1;
					invokevirtual 52;		// javacard/framework/APDU.setOutgoingLength(S)V
					aload_1;
					aload_3;
					sconst_0;
					sconst_1;
					invokevirtual 53;		// javacard/framework/APDU.sendBytesLong([BSS)V
					goto L10;
				L8:	sload 5;
					sconst_3;
					smul;
					sstore 6;
				L9:	aload_3;
					sconst_0;
					sconst_1;
					bastore;
					aload_3;
					sconst_1;
					getfield_a_this 37;		// reference ParkCard/GameManager.gameList
					sload 6;
					baload;
					bastore;
					aload_3;
					sconst_2;
					getfield_a_this 37;		// reference ParkCard/GameManager.gameList
					sload 6;
					sconst_1;
					sadd;
					baload;
					bastore;
					aload_3;
					sconst_3;
					getfield_a_this 37;		// reference ParkCard/GameManager.gameList
					sload 6;
					sconst_2;
					sadd;
					baload;
					bastore;
					aload_1;
					invokevirtual 51;		// javacard/framework/APDU.setOutgoing()S
					pop;
					aload_1;
					sconst_4;
					invokevirtual 52;		// javacard/framework/APDU.setOutgoingLength(S)V
					aload_1;
					aload_3;
					sconst_0;
					sconst_4;
					invokevirtual 53;		// javacard/framework/APDU.sendBytesLong([BSS)V
				L10:	return;
		}

		.method public removeGame(Ljavacard/framework/APDU;)V 6 {
			.stack 5;
			.locals 7;

			.descriptor	Ljavacard/framework/APDU;	2.10;

				L0:	aload_1;
					invokevirtual 176;		// javacard/framework/APDU.setIncomingAndReceive()S
					sstore_2;
				L1:	sload_2;
					sconst_2;
					if_scmpeq L3;
				L2:	sspush 26368;
					invokestatic 162;		// javacard/framework/ISOException.throwIt(S)V
				L3:	aload_1;
					invokevirtual 174;		// javacard/framework/APDU.getBuffer()[B
					astore_3;
				L4:	aload_3;
					sconst_5;
					baload;
					bspush 8;
					sshl;
					aload_3;
					bspush 6;
					baload;
					sspush 255;
					sand;
					sor;
					sstore 4;
				L5:	aload_0;
					sload 4;
					invokespecial 157;		// ParkCard/GameManager.findGameIndex(S)S
					sstore 5;
				L6:	sload 5;
					sconst_m1;
					if_scmpne L8;
				L7:	sspush 27266;
					invokestatic 162;		// javacard/framework/ISOException.throwIt(S)V
				L8:	sload 5;
					sconst_1;
					sadd;
					sconst_3;
					smul;
					sstore 6;
				L9:	sload 5;
					sconst_3;
					smul;
					sstore 7;
				L10:	aload_0;
					invokespecial 156;		// ParkCard/GameManager.getGameCount()S
					sload 5;
					ssub;
					sconst_1;
					ssub;
					sconst_3;
					smul;
					sstore 8;
				L11:	sload 8;
					ifle L13;
				L12:	getfield_a_this 37;		// reference ParkCard/GameManager.gameList
					sload 6;
					getfield_a_this 37;		// reference ParkCard/GameManager.gameList
					sload 7;
					sload 8;
					invokestatic 163;		// javacard/framework/Util.arrayCopyNonAtomic([BS[BSS)S
					pop;
				L13:	aload_0;
					aload_0;
					invokespecial 156;		// ParkCard/GameManager.getGameCount()S
					sconst_1;
					ssub;
					invokespecial 158;		// ParkCard/GameManager.setGameCount(S)V
					return;
		}

	}

	.class public PBKDF2 4 extends 0.0 {		// extends java/lang/Object

		.fields {
			private final 1.11 sha1 0;		// Ljavacard/security/MessageDigest;
			private final byte[] ipad 1;		// [B
			private final byte[] opad 2;		// [B
			private final byte[] innerHash 3;		// [B
			private static final short BLOCK_SIZE = 64;		// S
			private static final short HASH_SIZE = 20;		// S
		}

		.publicMethodTable 1 {
			equals(Ljava/lang/Object;)Z;
			deriveKey([BSS[BSSS[BS)V;
		}

		.packageMethodTable 0 {
		}

		.method public <init>()V 0 {
			.stack 3;
			.locals 0;

				L0:	aload_0;
					invokespecial 58;		// java/lang/Object.<init>()V
					aload_0;
					sconst_1;
					sconst_0;
					invokestatic 159;		// javacard/security/MessageDigest.getInstance(BZ)Ljavacard/security/MessageDigest;
					putfield_a 39;		// reference ParkCard/PBKDF2.sha1
					aload_0;
					bspush 64;
					newarray 11;
					putfield_a 40;		// reference ParkCard/PBKDF2.ipad
					aload_0;
					bspush 64;
					newarray 11;
					putfield_a 41;		// reference ParkCard/PBKDF2.opad
					aload_0;
					bspush 20;
					newarray 11;
					putfield_a 42;		// reference ParkCard/PBKDF2.innerHash
					return;
		}

		.method private hmac([BSS[BSS[BS)V {
			.stack 6;
			.locals 1;

				L0:	getfield_a_this 40;		// reference ParkCard/PBKDF2.ipad
					sconst_0;
					bspush 64;
					sconst_0;
					invokestatic 155;		// javacard/framework/Util.arrayFillNonAtomic([BSSB)S
					pop;
					getfield_a_this 41;		// reference ParkCard/PBKDF2.opad
					sconst_0;
					bspush 64;
					sconst_0;
					invokestatic 155;		// javacard/framework/Util.arrayFillNonAtomic([BSSB)S
					pop;
					sload_3;
					bspush 64;
					if_scmpgt L2;
				L1:	aload_1;
					sload_2;
					getfield_a_this 40;		// reference ParkCard/PBKDF2.ipad
					sconst_0;
					sload_3;
					invokestatic 163;		// javacard/framework/Util.arrayCopyNonAtomic([BS[BSS)S
					pop;
					aload_1;
					sload_2;
					getfield_a_this 41;		// reference ParkCard/PBKDF2.opad
					sconst_0;
					sload_3;
					invokestatic 163;		// javacard/framework/Util.arrayCopyNonAtomic([BS[BSS)S
					pop;
					goto L3;
				L2:	getfield_a_this 39;		// reference ParkCard/PBKDF2.sha1
					invokevirtual 164;		// javacard/security/MessageDigest.reset()V
					getfield_a_this 39;		// reference ParkCard/PBKDF2.sha1
					aload_1;
					sload_2;
					sload_3;
					getfield_a_this 40;		// reference ParkCard/PBKDF2.ipad
					sconst_0;
					invokevirtual 165;		// javacard/security/MessageDigest.doFinal([BSS[BS)S
					pop;
					getfield_a_this 40;		// reference ParkCard/PBKDF2.ipad
					sconst_0;
					getfield_a_this 41;		// reference ParkCard/PBKDF2.opad
					sconst_0;
					bspush 20;
					invokestatic 163;		// javacard/framework/Util.arrayCopyNonAtomic([BS[BSS)S
					pop;
				L3:	sconst_0;
					sstore 9;
				L4:	sload 9;
					bspush 64;
					if_scmpge L6;
				L5:	getfield_a_this 40;		// reference ParkCard/PBKDF2.ipad
					sload 9;
					dup2;
					baload;
					bspush 54;
					sxor;
					bastore;
					getfield_a_this 41;		// reference ParkCard/PBKDF2.opad
					sload 9;
					dup2;
					baload;
					bspush 92;
					sxor;
					bastore;
					sinc 9 1;
					goto L4;
				L6:	getfield_a_this 39;		// reference ParkCard/PBKDF2.sha1
					invokevirtual 164;		// javacard/security/MessageDigest.reset()V
					getfield_a_this 39;		// reference ParkCard/PBKDF2.sha1
					getfield_a_this 40;		// reference ParkCard/PBKDF2.ipad
					sconst_0;
					bspush 64;
					invokevirtual 166;		// javacard/security/MessageDigest.update([BSS)V
					getfield_a_this 39;		// reference ParkCard/PBKDF2.sha1
					aload 4;
					sload 5;
					sload 6;
					getfield_a_this 42;		// reference ParkCard/PBKDF2.innerHash
					sconst_0;
					invokevirtual 165;		// javacard/security/MessageDigest.doFinal([BSS[BS)S
					pop;
					getfield_a_this 39;		// reference ParkCard/PBKDF2.sha1
					invokevirtual 164;		// javacard/security/MessageDigest.reset()V
					getfield_a_this 39;		// reference ParkCard/PBKDF2.sha1
					getfield_a_this 41;		// reference ParkCard/PBKDF2.opad
					sconst_0;
					bspush 64;
					invokevirtual 166;		// javacard/security/MessageDigest.update([BSS)V
					getfield_a_this 39;		// reference ParkCard/PBKDF2.sha1
					getfield_a_this 42;		// reference ParkCard/PBKDF2.innerHash
					sconst_0;
					bspush 20;
					aload 7;
					sload 8;
					invokevirtual 165;		// javacard/security/MessageDigest.doFinal([BSS[BS)S
					pop;
					return;
		}

		.method public deriveKey([BSS[BSSS[BS)V 1 {
			.stack 9;
			.locals 6;

				L0:	bspush 20;
					sconst_2;
					invokestatic 77;		// javacard/framework/JCSystem.makeTransientByteArray(SB)[B
					astore 10;
				L1:	bspush 20;
					sconst_2;
					invokestatic 77;		// javacard/framework/JCSystem.makeTransientByteArray(SB)[B
					astore 11;
				L2:	sload 6;
					sconst_4;
					sadd;
					sstore 12;
				L3:	sload 12;
					sconst_2;
					invokestatic 77;		// javacard/framework/JCSystem.makeTransientByteArray(SB)[B
					astore 13;
				L4:	aload 4;
					sload 5;
					aload 13;
					sconst_0;
					sload 6;
					invokestatic 163;		// javacard/framework/Util.arrayCopyNonAtomic([BS[BSS)S
					pop;
					aload 13;
					sload 6;
					sconst_0;
					bastore;
					aload 13;
					sload 6;
					sconst_1;
					sadd;
					sconst_0;
					bastore;
					aload 13;
					sload 6;
					sconst_2;
					sadd;
					sconst_0;
					bastore;
					aload 13;
					sload 6;
					sconst_3;
					sadd;
					sconst_1;
					bastore;
					aload_0;
					aload_1;
					sload_2;
					sload_3;
					aload 13;
					sconst_0;
					sload 12;
					aload 10;
					sconst_0;
					invokespecial 167;		// ParkCard/PBKDF2.hmac([BSS[BSS[BS)V
					aload 10;
					sconst_0;
					aload 11;
					sconst_0;
					bspush 20;
					invokestatic 163;		// javacard/framework/Util.arrayCopyNonAtomic([BS[BSS)S
					pop;
					sconst_1;
					sstore 14;
				L5:	sload 14;
					sload 7;
					if_scmpge L10;
				L6:	aload_0;
					aload_1;
					sload_2;
					sload_3;
					aload 10;
					sconst_0;
					bspush 20;
					aload 10;
					sconst_0;
					invokespecial 167;		// ParkCard/PBKDF2.hmac([BSS[BSS[BS)V
					sconst_0;
					sstore 15;
				L7:	sload 15;
					bspush 20;
					if_scmpge L9;
				L8:	aload 11;
					sload 15;
					dup2;
					baload;
					aload 10;
					sload 15;
					baload;
					sxor;
					bastore;
					sinc 15 1;
					goto L7;
				L9:	sinc 14 1;
					goto L5;
				L10:	aload 11;
					sconst_0;
					aload 8;
					sload 9;
					bspush 20;
					invokestatic 163;		// javacard/framework/Util.arrayCopyNonAtomic([BS[BSS)S
					pop;
					return;
		}

	}

	.class public PinManager 5 extends 0.0 {		// extends java/lang/Object

		.fields {
			private 2.9 userPIN 0;		// Ljavacard/framework/OwnerPIN;
			private 2.9 adminPIN 1;		// Ljavacard/framework/OwnerPIN;
			private 2.9 pukPIN 2;		// Ljavacard/framework/OwnerPIN;
			private CryptoManager cryptoManager 3;		// LParkCard/CryptoManager;
			private CardModel cardModel 4;		// LParkCard/CardModel;
			private boolean pinCreated 5;		// Z
			private boolean adminPinCreated 6;		// Z
			private static final byte PIN_MIN_LENGTH = 4;		// B
			private static final byte PIN_MAX_LENGTH = 8;		// B
			private static final byte PIN_MAX_TRIES = 3;		// B
			private static final byte ADMIN_PIN_MAX_TRIES = 5;		// B
			private static final byte PUK_LENGTH = 8;		// B
			private static final byte PUK_MAX_TRIES = 5;		// B
		}

		.publicMethodTable 1 {
			equals(Ljava/lang/Object;)Z;
			setCryptoManager(LParkCard/CryptoManager;)V;
			setCardModel(LParkCard/CardModel;)V;
			isPINValidated()Z;
			isAdminPINValidated()Z;
			createPIN(Ljavacard/framework/APDU;)V;
			verify([BSB)Z;
			getTriesRemaining()B;
			changePIN(Ljavacard/framework/APDU;)V;
			getPinTries(Ljavacard/framework/APDU;)V;
			getAdminPinTries(Ljavacard/framework/APDU;)V;
			resetPinCounter(Ljavacard/framework/APDU;)V;
			resetWithPUK(Ljavacard/framework/APDU;)V;
			verifyAdmin([BSB)Z;
			getAdminTriesRemaining()B;
			changeAdminPIN(Ljavacard/framework/APDU;)V;
			resetUserPIN(Ljavacard/framework/APDU;)V;
		}

		.packageMethodTable 0 {
		}

		.method public <init>()V 0 {
			.stack 5;
			.locals 3;

				L0:	aload_0;
					invokespecial 58;		// java/lang/Object.<init>()V
					aload_0;
					new 168;		// javacard/framework/OwnerPIN
					dup;
					sconst_3;
					bspush 8;
					invokespecial 169;		// javacard/framework/OwnerPIN.<init>(BB)V
					putfield_a 43;		// reference ParkCard/PinManager.userPIN
					aload_0;
					new 168;		// javacard/framework/OwnerPIN
					dup;
					sconst_5;
					bspush 8;
					invokespecial 169;		// javacard/framework/OwnerPIN.<init>(BB)V
					putfield_a 44;		// reference ParkCard/PinManager.adminPIN
					aload_0;
					new 168;		// javacard/framework/OwnerPIN
					dup;
					sconst_5;
					bspush 8;
					invokespecial 169;		// javacard/framework/OwnerPIN.<init>(BB)V
					putfield_a 45;		// reference ParkCard/PinManager.pukPIN
					aload_0;
					sconst_0;
					putfield_b 46;		// boolean ParkCard/PinManager.pinCreated
					aload_0;
					sconst_0;
					putfield_b 47;		// boolean ParkCard/PinManager.adminPinCreated
					sconst_4;
					newarray 11;
					dup;
					sconst_0;
					bspush 49;
					bastore;
					dup;
					sconst_1;
					bspush 50;
					bastore;
					dup;
					sconst_2;
					bspush 51;
					bastore;
					dup;
					sconst_3;
					bspush 52;
					bastore;
					astore_1;
				L1:	getfield_a_this 43;		// reference ParkCard/PinManager.userPIN
					aload_1;
					sconst_0;
					sconst_4;
					invokevirtual 175;		// javacard/framework/OwnerPIN.update([BSB)V
					aload_0;
					sconst_1;
					putfield_b 46;		// boolean ParkCard/PinManager.pinCreated
					sconst_4;
					newarray 11;
					dup;
					sconst_0;
					bspush 57;
					bastore;
					dup;
					sconst_1;
					bspush 57;
					bastore;
					dup;
					sconst_2;
					bspush 57;
					bastore;
					dup;
					sconst_3;
					bspush 57;
					bastore;
					astore_2;
				L2:	getfield_a_this 44;		// reference ParkCard/PinManager.adminPIN
					aload_2;
					sconst_0;
					sconst_4;
					invokevirtual 175;		// javacard/framework/OwnerPIN.update([BSB)V
					aload_0;
					sconst_1;
					putfield_b 47;		// boolean ParkCard/PinManager.adminPinCreated
					bspush 8;
					newarray 11;
					dup;
					sconst_0;
					bspush 56;
					bastore;
					dup;
					sconst_1;
					bspush 55;
					bastore;
					dup;
					sconst_2;
					bspush 54;
					bastore;
					dup;
					sconst_3;
					bspush 53;
					bastore;
					dup;
					sconst_4;
					bspush 52;
					bastore;
					dup;
					sconst_5;
					bspush 51;
					bastore;
					dup;
					bspush 6;
					bspush 50;
					bastore;
					dup;
					bspush 7;
					bspush 49;
					bastore;
					astore_3;
				L3:	getfield_a_this 45;		// reference ParkCard/PinManager.pukPIN
					aload_3;
					sconst_0;
					bspush 8;
					invokevirtual 175;		// javacard/framework/OwnerPIN.update([BSB)V
					return;
		}

		.method public setCryptoManager(LParkCard/CryptoManager;)V 1 {
			.stack 2;
			.locals 0;

				L0:	aload_0;
					aload_1;
					putfield_a 48;		// reference ParkCard/PinManager.cryptoManager
					return;
		}

		.method public setCardModel(LParkCard/CardModel;)V 2 {
			.stack 2;
			.locals 0;

				L0:	aload_0;
					aload_1;
					putfield_a 49;		// reference ParkCard/PinManager.cardModel
					return;
		}

		.method public isPINValidated()Z 3 {
			.stack 1;
			.locals 0;

				L0:	getfield_a_this 43;		// reference ParkCard/PinManager.userPIN
					invokevirtual 178;		// javacard/framework/OwnerPIN.isValidated()Z
					sreturn;
		}

		.method public isAdminPINValidated()Z 4 {
			.stack 1;
			.locals 0;

				L0:	getfield_a_this 44;		// reference ParkCard/PinManager.adminPIN
					invokevirtual 178;		// javacard/framework/OwnerPIN.isValidated()Z
					sreturn;
		}

		.method public createPIN(Ljavacard/framework/APDU;)V 5 {
			.stack 4;
			.locals 2;

			.descriptor	Ljavacard/framework/APDU;	2.10;

				L0:	getfield_b_this 46;		// boolean ParkCard/PinManager.pinCreated
					ifeq L2;
				L1:	sspush 27013;
					invokestatic 162;		// javacard/framework/ISOException.throwIt(S)V
				L2:	aload_1;
					invokevirtual 174;		// javacard/framework/APDU.getBuffer()[B
					astore_2;
				L3:	aload_1;
					invokevirtual 176;		// javacard/framework/APDU.setIncomingAndReceive()S
					sstore_3;
				L4:	sload_3;
					sconst_4;
					if_scmplt L6;
				L5:	sload_3;
					bspush 8;
					if_scmple L7;
				L6:	sspush 26368;
					invokestatic 162;		// javacard/framework/ISOException.throwIt(S)V
				L7:	getfield_a_this 43;		// reference ParkCard/PinManager.userPIN
					aload_2;
					sconst_5;
					sload_3;
					s2b;
					invokevirtual 175;		// javacard/framework/OwnerPIN.update([BSB)V
					aload_0;
					sconst_1;
					putfield_b 46;		// boolean ParkCard/PinManager.pinCreated
					return;
		}

		.method public verify([BSB)Z 6 {
			.stack 7;
			.locals 1;

				L0:	getfield_b_this 46;		// boolean ParkCard/PinManager.pinCreated
					ifne L2;
				L1:	sspush 27013;
					invokestatic 162;		// javacard/framework/ISOException.throwIt(S)V
				L2:	getfield_a_this 43;		// reference ParkCard/PinManager.userPIN
					aload_1;
					sload_2;
					sload_3;
					invokevirtual 179;		// javacard/framework/OwnerPIN.check([BSB)Z
					ifeq L10;
				L3:	getfield_a_this 48;		// reference ParkCard/PinManager.cryptoManager
					ifnull L9;
				L4:	getfield_a_this 49;		// reference ParkCard/PinManager.cardModel
					ifnull L9;
				L5:	getfield_a_this 49;		// reference ParkCard/PinManager.cardModel
					invokevirtual 139;		// ParkCard/CardModel.getSalt()[B
					astore 4;
				L6:	getfield_a_this 48;		// reference ParkCard/PinManager.cryptoManager
					aload_1;
					sload_2;
					sload_3;
					aload 4;
					sconst_0;
					bspush 16;
					invokevirtual 180;		// ParkCard/CryptoManager.deriveKeyFromPIN([BSB[BSS)V
					getfield_a_this 49;		// reference ParkCard/PinManager.cardModel
					invokevirtual 181;		// ParkCard/CardModel.isMasterKeyWrapped()Z
					ifeq L8;
				L7:	getfield_a_this 48;		// reference ParkCard/PinManager.cryptoManager
					getfield_a_this 49;		// reference ParkCard/PinManager.cardModel
					invokevirtual 182;		// ParkCard/CardModel.getWrappedMasterKey()[B
					sconst_0;
					getfield_a_this 49;		// reference ParkCard/PinManager.cardModel
					invokevirtual 138;		// ParkCard/CardModel.getIV()[B
					sconst_0;
					invokevirtual 183;		// ParkCard/CryptoManager.unwrapMasterKey([BS[BS)V
					goto L9;
				L8:	getfield_a_this 49;		// reference ParkCard/PinManager.cardModel
					getfield_a_this 48;		// reference ParkCard/PinManager.cryptoManager
					invokevirtual 184;		// ParkCard/CardModel.ensureMasterKey(LParkCard/CryptoManager;)V
					getfield_a_this 48;		// reference ParkCard/PinManager.cryptoManager
					getfield_a_this 49;		// reference ParkCard/PinManager.cardModel
					invokevirtual 182;		// ParkCard/CardModel.getWrappedMasterKey()[B
					sconst_0;
					getfield_a_this 49;		// reference ParkCard/PinManager.cardModel
					invokevirtual 138;		// ParkCard/CardModel.getIV()[B
					sconst_0;
					invokevirtual 183;		// ParkCard/CryptoManager.unwrapMasterKey([BS[BS)V
				L9:	sconst_1;
					sreturn;
				L10:	sconst_0;
					sreturn;
		}

		.method public getTriesRemaining()B 7 {
			.stack 1;
			.locals 0;

				L0:	getfield_a_this 43;		// reference ParkCard/PinManager.userPIN
					invokevirtual 185;		// javacard/framework/OwnerPIN.getTriesRemaining()B
					sreturn;
		}

		.method public changePIN(Ljavacard/framework/APDU;)V 8 {
			.stack 8;
			.locals 7;

			.descriptor	Ljavacard/framework/APDU;	2.10;

				L0:	aload_1;
					invokevirtual 174;		// javacard/framework/APDU.getBuffer()[B
					astore_2;
				L1:	aload_1;
					invokevirtual 176;		// javacard/framework/APDU.setIncomingAndReceive()S
					pop;
					aload_2;
					sconst_5;
					baload;
					sstore_3;
				L2:	bspush 6;
					sstore 4;
				L3:	aload_2;
					sload 4;
					sload_3;
					sadd;
					baload;
					sstore 5;
				L4:	sload 4;
					sload_3;
					sadd;
					sconst_1;
					sadd;
					sstore 6;
				L5:	sload 5;
					sconst_4;
					if_scmplt L7;
				L6:	sload 5;
					bspush 8;
					if_scmple L8;
				L7:	sspush 26368;
					invokestatic 162;		// javacard/framework/ISOException.throwIt(S)V
				L8:	getfield_a_this 43;		// reference ParkCard/PinManager.userPIN
					aload_2;
					sload 4;
					sload_3;
					invokevirtual 179;		// javacard/framework/OwnerPIN.check([BSB)Z
					ifne L10;
				L9:	sspush 25536;
					getfield_a_this 43;		// reference ParkCard/PinManager.userPIN
					invokevirtual 185;		// javacard/framework/OwnerPIN.getTriesRemaining()B
					sor;
					invokestatic 162;		// javacard/framework/ISOException.throwIt(S)V
				L10:	getfield_a_this 49;		// reference ParkCard/PinManager.cardModel
					ifnull L16;
				L11:	getfield_a_this 48;		// reference ParkCard/PinManager.cryptoManager
					ifnull L16;
				L12:	getfield_a_this 48;		// reference ParkCard/PinManager.cryptoManager
					invokevirtual 160;		// ParkCard/CryptoManager.isKeyReady()Z
					ifeq L16;
				L13:	getfield_a_this 49;		// reference ParkCard/PinManager.cardModel
					invokevirtual 139;		// ParkCard/CardModel.getSalt()[B
					astore 7;
				L14:	getfield_a_this 49;		// reference ParkCard/PinManager.cardModel
					invokevirtual 138;		// ParkCard/CardModel.getIV()[B
					astore 8;
				L15:	getfield_a_this 48;		// reference ParkCard/PinManager.cryptoManager
					aload_2;
					sload 6;
					sload 5;
					aload 7;
					sconst_0;
					bspush 16;
					sconst_1;
					invokevirtual 68;		// ParkCard/CryptoManager.deriveKeyFromPIN([BSB[BSSZ)V
					getfield_a_this 48;		// reference ParkCard/PinManager.cryptoManager
					getfield_a_this 49;		// reference ParkCard/PinManager.cardModel
					invokevirtual 182;		// ParkCard/CardModel.getWrappedMasterKey()[B
					sconst_0;
					aload 8;
					sconst_0;
					invokevirtual 161;		// ParkCard/CryptoManager.wrapLoadedMasterKey([BS[BS)V
				L16:	getfield_a_this 43;		// reference ParkCard/PinManager.userPIN
					aload_2;
					sload 6;
					sload 5;
					invokevirtual 175;		// javacard/framework/OwnerPIN.update([BSB)V
					getfield_a_this 43;		// reference ParkCard/PinManager.userPIN
					aload_2;
					sload 6;
					sload 5;
					invokevirtual 179;		// javacard/framework/OwnerPIN.check([BSB)Z
					pop;
					return;
		}

		.method public getPinTries(Ljavacard/framework/APDU;)V 9 {
			.stack 4;
			.locals 1;

			.descriptor	Ljavacard/framework/APDU;	2.10;

				L0:	aload_1;
					invokevirtual 174;		// javacard/framework/APDU.getBuffer()[B
					astore_2;
				L1:	aload_2;
					sconst_0;
					getfield_a_this 43;		// reference ParkCard/PinManager.userPIN
					invokevirtual 185;		// javacard/framework/OwnerPIN.getTriesRemaining()B
					bastore;
					aload_2;
					sconst_1;
					getfield_b_this 46;		// boolean ParkCard/PinManager.pinCreated
					ifeq L3;
				L2:	sconst_1;
					goto L4;
				L3:	sconst_0;
				L4:	bastore;
					aload_2;
					sconst_2;
					getfield_a_this 43;		// reference ParkCard/PinManager.userPIN
					invokevirtual 178;		// javacard/framework/OwnerPIN.isValidated()Z
					ifeq L6;
				L5:	sconst_1;
					goto L7;
				L6:	sconst_0;
				L7:	bastore;
					aload_1;
					invokevirtual 51;		// javacard/framework/APDU.setOutgoing()S
					pop;
					aload_1;
					sconst_3;
					invokevirtual 52;		// javacard/framework/APDU.setOutgoingLength(S)V
					aload_1;
					aload_2;
					sconst_0;
					sconst_3;
					invokevirtual 53;		// javacard/framework/APDU.sendBytesLong([BSS)V
					return;
		}

		.method public getAdminPinTries(Ljavacard/framework/APDU;)V 10 {
			.stack 4;
			.locals 1;

			.descriptor	Ljavacard/framework/APDU;	2.10;

				L0:	aload_1;
					invokevirtual 174;		// javacard/framework/APDU.getBuffer()[B
					astore_2;
				L1:	aload_2;
					sconst_0;
					getfield_a_this 44;		// reference ParkCard/PinManager.adminPIN
					invokevirtual 185;		// javacard/framework/OwnerPIN.getTriesRemaining()B
					bastore;
					aload_2;
					sconst_1;
					getfield_b_this 47;		// boolean ParkCard/PinManager.adminPinCreated
					ifeq L3;
				L2:	sconst_1;
					goto L4;
				L3:	sconst_0;
				L4:	bastore;
					aload_2;
					sconst_2;
					getfield_a_this 44;		// reference ParkCard/PinManager.adminPIN
					invokevirtual 178;		// javacard/framework/OwnerPIN.isValidated()Z
					ifeq L6;
				L5:	sconst_1;
					goto L7;
				L6:	sconst_0;
				L7:	bastore;
					aload_1;
					invokevirtual 51;		// javacard/framework/APDU.setOutgoing()S
					pop;
					aload_1;
					sconst_3;
					invokevirtual 52;		// javacard/framework/APDU.setOutgoingLength(S)V
					aload_1;
					aload_2;
					sconst_0;
					sconst_3;
					invokevirtual 53;		// javacard/framework/APDU.sendBytesLong([BSS)V
					return;
		}

		.method public resetPinCounter(Ljavacard/framework/APDU;)V 11 {
			.stack 1;
			.locals 0;

			.descriptor	Ljavacard/framework/APDU;	2.10;

				L0:	getfield_a_this 43;		// reference ParkCard/PinManager.userPIN
					invokevirtual 186;		// javacard/framework/OwnerPIN.resetAndUnblock()V
					return;
		}

		.method public resetWithPUK(Ljavacard/framework/APDU;)V 12 {
			.stack 7;
			.locals 4;

			.descriptor	Ljavacard/framework/APDU;	2.10;

				L0:	aload_1;
					invokevirtual 174;		// javacard/framework/APDU.getBuffer()[B
					astore_2;
				L1:	aload_1;
					invokevirtual 176;		// javacard/framework/APDU.setIncomingAndReceive()S
					pop;
					getfield_a_this 45;		// reference ParkCard/PinManager.pukPIN
					aload_2;
					sconst_5;
					bspush 8;
					invokevirtual 179;		// javacard/framework/OwnerPIN.check([BSB)Z
					ifne L3;
				L2:	sspush 25536;
					invokestatic 162;		// javacard/framework/ISOException.throwIt(S)V
				L3:	aload_2;
					bspush 13;
					baload;
					sstore_3;
				L4:	bspush 14;
					sstore 4;
				L5:	sload_3;
					sconst_4;
					if_scmplt L7;
				L6:	sload_3;
					bspush 8;
					if_scmple L8;
				L7:	sspush 26368;
					invokestatic 162;		// javacard/framework/ISOException.throwIt(S)V
				L8:	getfield_a_this 49;		// reference ParkCard/PinManager.cardModel
					ifnull L14;
				L9:	getfield_a_this 48;		// reference ParkCard/PinManager.cryptoManager
					ifnull L14;
				L10:	getfield_a_this 49;		// reference ParkCard/PinManager.cardModel
					invokevirtual 139;		// ParkCard/CardModel.getSalt()[B
					astore 5;
				L11:	getfield_a_this 48;		// reference ParkCard/PinManager.cryptoManager
					aload_2;
					sload 4;
					sload_3;
					aload 5;
					sconst_0;
					bspush 16;
					invokevirtual 180;		// ParkCard/CryptoManager.deriveKeyFromPIN([BSB[BSS)V
					getfield_a_this 49;		// reference ParkCard/PinManager.cardModel
					invokevirtual 181;		// ParkCard/CardModel.isMasterKeyWrapped()Z
					ifne L13;
				L12:	getfield_a_this 49;		// reference ParkCard/PinManager.cardModel
					getfield_a_this 48;		// reference ParkCard/PinManager.cryptoManager
					invokevirtual 184;		// ParkCard/CardModel.ensureMasterKey(LParkCard/CryptoManager;)V
				L13:	getfield_a_this 49;		// reference ParkCard/PinManager.cardModel
					sconst_1;
					invokevirtual 187;		// ParkCard/CardModel.setMasterKeyWrapped(Z)V
					getfield_a_this 48;		// reference ParkCard/PinManager.cryptoManager
					invokevirtual 133;		// ParkCard/CryptoManager.clearKey()V
				L14:	getfield_a_this 43;		// reference ParkCard/PinManager.userPIN
					aload_2;
					sload 4;
					sload_3;
					invokevirtual 175;		// javacard/framework/OwnerPIN.update([BSB)V
					aload_0;
					sconst_1;
					putfield_b 46;		// boolean ParkCard/PinManager.pinCreated
					getfield_a_this 43;		// reference ParkCard/PinManager.userPIN
					invokevirtual 186;		// javacard/framework/OwnerPIN.resetAndUnblock()V
					return;
		}

		.method public verifyAdmin([BSB)Z 13 {
			.stack 7;
			.locals 1;

				L0:	getfield_b_this 47;		// boolean ParkCard/PinManager.adminPinCreated
					ifne L2;
				L1:	sspush 27013;
					invokestatic 162;		// javacard/framework/ISOException.throwIt(S)V
				L2:	getfield_a_this 44;		// reference ParkCard/PinManager.adminPIN
					aload_1;
					sload_2;
					sload_3;
					invokevirtual 179;		// javacard/framework/OwnerPIN.check([BSB)Z
					ifeq L10;
				L3:	getfield_a_this 48;		// reference ParkCard/PinManager.cryptoManager
					ifnull L9;
				L4:	getfield_a_this 49;		// reference ParkCard/PinManager.cardModel
					ifnull L9;
				L5:	getfield_a_this 49;		// reference ParkCard/PinManager.cardModel
					invokevirtual 139;		// ParkCard/CardModel.getSalt()[B
					astore 4;
				L6:	getfield_a_this 48;		// reference ParkCard/PinManager.cryptoManager
					aload_1;
					sload_2;
					sload_3;
					aload 4;
					sconst_0;
					bspush 16;
					invokevirtual 180;		// ParkCard/CryptoManager.deriveKeyFromPIN([BSB[BSS)V
					getfield_a_this 49;		// reference ParkCard/PinManager.cardModel
					invokevirtual 188;		// ParkCard/CardModel.isMasterKeyWrappedAdmin()Z
					ifeq L8;
				L7:	getfield_a_this 48;		// reference ParkCard/PinManager.cryptoManager
					getfield_a_this 49;		// reference ParkCard/PinManager.cardModel
					invokevirtual 189;		// ParkCard/CardModel.getWrappedMasterKeyAdmin()[B
					sconst_0;
					getfield_a_this 49;		// reference ParkCard/PinManager.cardModel
					invokevirtual 138;		// ParkCard/CardModel.getIV()[B
					sconst_0;
					invokevirtual 183;		// ParkCard/CryptoManager.unwrapMasterKey([BS[BS)V
					goto L9;
				L8:	getfield_a_this 49;		// reference ParkCard/PinManager.cardModel
					getfield_a_this 48;		// reference ParkCard/PinManager.cryptoManager
					sconst_1;
					invokevirtual 190;		// ParkCard/CardModel.ensureMasterKeyWithAdmin(LParkCard/CryptoManager;Z)V
					getfield_a_this 48;		// reference ParkCard/PinManager.cryptoManager
					getfield_a_this 49;		// reference ParkCard/PinManager.cardModel
					invokevirtual 189;		// ParkCard/CardModel.getWrappedMasterKeyAdmin()[B
					sconst_0;
					getfield_a_this 49;		// reference ParkCard/PinManager.cardModel
					invokevirtual 138;		// ParkCard/CardModel.getIV()[B
					sconst_0;
					invokevirtual 183;		// ParkCard/CryptoManager.unwrapMasterKey([BS[BS)V
					aload_0;
					invokespecial 191;		// ParkCard/PinManager.syncMasterKeyToUserPIN()V
				L9:	sconst_1;
					sreturn;
				L10:	sconst_0;
					sreturn;
		}

		.method public getAdminTriesRemaining()B 14 {
			.stack 1;
			.locals 0;

				L0:	getfield_a_this 44;		// reference ParkCard/PinManager.adminPIN
					invokevirtual 185;		// javacard/framework/OwnerPIN.getTriesRemaining()B
					sreturn;
		}

		.method public changeAdminPIN(Ljavacard/framework/APDU;)V 15 {
			.stack 8;
			.locals 7;

			.descriptor	Ljavacard/framework/APDU;	2.10;

				L0:	aload_1;
					invokevirtual 174;		// javacard/framework/APDU.getBuffer()[B
					astore_2;
				L1:	aload_1;
					invokevirtual 176;		// javacard/framework/APDU.setIncomingAndReceive()S
					pop;
					aload_2;
					sconst_5;
					baload;
					sstore_3;
				L2:	bspush 6;
					sstore 4;
				L3:	aload_2;
					sload 4;
					sload_3;
					sadd;
					baload;
					sstore 5;
				L4:	sload 4;
					sload_3;
					sadd;
					sconst_1;
					sadd;
					sstore 6;
				L5:	sload 5;
					sconst_4;
					if_scmplt L7;
				L6:	sload 5;
					bspush 8;
					if_scmple L8;
				L7:	sspush 26368;
					invokestatic 162;		// javacard/framework/ISOException.throwIt(S)V
				L8:	getfield_a_this 44;		// reference ParkCard/PinManager.adminPIN
					aload_2;
					sload 4;
					sload_3;
					invokevirtual 179;		// javacard/framework/OwnerPIN.check([BSB)Z
					ifne L10;
				L9:	sspush 25536;
					getfield_a_this 44;		// reference ParkCard/PinManager.adminPIN
					invokevirtual 185;		// javacard/framework/OwnerPIN.getTriesRemaining()B
					sor;
					invokestatic 162;		// javacard/framework/ISOException.throwIt(S)V
				L10:	getfield_a_this 49;		// reference ParkCard/PinManager.cardModel
					ifnull L16;
				L11:	getfield_a_this 48;		// reference ParkCard/PinManager.cryptoManager
					ifnull L16;
				L12:	getfield_a_this 48;		// reference ParkCard/PinManager.cryptoManager
					invokevirtual 160;		// ParkCard/CryptoManager.isKeyReady()Z
					ifeq L16;
				L13:	getfield_a_this 49;		// reference ParkCard/PinManager.cardModel
					invokevirtual 139;		// ParkCard/CardModel.getSalt()[B
					astore 7;
				L14:	getfield_a_this 49;		// reference ParkCard/PinManager.cardModel
					invokevirtual 138;		// ParkCard/CardModel.getIV()[B
					astore 8;
				L15:	getfield_a_this 48;		// reference ParkCard/PinManager.cryptoManager
					aload_2;
					sload 6;
					sload 5;
					aload 7;
					sconst_0;
					bspush 16;
					sconst_1;
					invokevirtual 68;		// ParkCard/CryptoManager.deriveKeyFromPIN([BSB[BSSZ)V
					getfield_a_this 48;		// reference ParkCard/PinManager.cryptoManager
					getfield_a_this 49;		// reference ParkCard/PinManager.cardModel
					invokevirtual 189;		// ParkCard/CardModel.getWrappedMasterKeyAdmin()[B
					sconst_0;
					aload 8;
					sconst_0;
					invokevirtual 161;		// ParkCard/CryptoManager.wrapLoadedMasterKey([BS[BS)V
				L16:	getfield_a_this 44;		// reference ParkCard/PinManager.adminPIN
					aload_2;
					sload 6;
					sload 5;
					invokevirtual 175;		// javacard/framework/OwnerPIN.update([BSB)V
					getfield_a_this 44;		// reference ParkCard/PinManager.adminPIN
					aload_2;
					sload 6;
					sload 5;
					invokevirtual 179;		// javacard/framework/OwnerPIN.check([BSB)Z
					pop;
					return;
		}

		.method public resetUserPIN(Ljavacard/framework/APDU;)V 16 {
			.stack 8;
			.locals 5;

			.descriptor	Ljavacard/framework/APDU;	2.10;

				L0:	getfield_a_this 44;		// reference ParkCard/PinManager.adminPIN
					invokevirtual 178;		// javacard/framework/OwnerPIN.isValidated()Z
					ifne L2;
				L1:	sspush 27010;
					invokestatic 162;		// javacard/framework/ISOException.throwIt(S)V
				L2:	getfield_a_this 48;		// reference ParkCard/PinManager.cryptoManager
					ifnull L4;
				L3:	getfield_a_this 48;		// reference ParkCard/PinManager.cryptoManager
					invokevirtual 160;		// ParkCard/CryptoManager.isKeyReady()Z
					ifne L5;
				L4:	sspush 27013;
					invokestatic 162;		// javacard/framework/ISOException.throwIt(S)V
				L5:	aload_1;
					invokevirtual 174;		// javacard/framework/APDU.getBuffer()[B
					astore_2;
				L6:	aload_1;
					invokevirtual 176;		// javacard/framework/APDU.setIncomingAndReceive()S
					pop;
					aload_2;
					sconst_5;
					baload;
					sstore_3;
				L7:	bspush 6;
					sstore 4;
				L8:	sload_3;
					sconst_4;
					if_scmplt L10;
				L9:	sload_3;
					bspush 8;
					if_scmple L11;
				L10:	sspush 26368;
					invokestatic 162;		// javacard/framework/ISOException.throwIt(S)V
				L11:	getfield_a_this 49;		// reference ParkCard/PinManager.cardModel
					ifnull L16;
				L12:	getfield_a_this 48;		// reference ParkCard/PinManager.cryptoManager
					ifnull L16;
				L13:	getfield_a_this 49;		// reference ParkCard/PinManager.cardModel
					invokevirtual 139;		// ParkCard/CardModel.getSalt()[B
					astore 5;
				L14:	getfield_a_this 49;		// reference ParkCard/PinManager.cardModel
					invokevirtual 138;		// ParkCard/CardModel.getIV()[B
					astore 6;
				L15:	getfield_a_this 48;		// reference ParkCard/PinManager.cryptoManager
					aload_2;
					sload 4;
					sload_3;
					aload 5;
					sconst_0;
					bspush 16;
					sconst_1;
					invokevirtual 68;		// ParkCard/CryptoManager.deriveKeyFromPIN([BSB[BSSZ)V
					getfield_a_this 48;		// reference ParkCard/PinManager.cryptoManager
					getfield_a_this 49;		// reference ParkCard/PinManager.cardModel
					invokevirtual 182;		// ParkCard/CardModel.getWrappedMasterKey()[B
					sconst_0;
					aload 6;
					sconst_0;
					invokevirtual 161;		// ParkCard/CryptoManager.wrapLoadedMasterKey([BS[BS)V
					getfield_a_this 49;		// reference ParkCard/PinManager.cardModel
					sconst_1;
					invokevirtual 187;		// ParkCard/CardModel.setMasterKeyWrapped(Z)V
				L16:	getfield_a_this 43;		// reference ParkCard/PinManager.userPIN
					aload_2;
					sload 4;
					sload_3;
					invokevirtual 175;		// javacard/framework/OwnerPIN.update([BSB)V
					aload_0;
					sconst_1;
					putfield_b 46;		// boolean ParkCard/PinManager.pinCreated
					getfield_a_this 43;		// reference ParkCard/PinManager.userPIN
					invokevirtual 186;		// javacard/framework/OwnerPIN.resetAndUnblock()V
					return;
		}

		.method private syncMasterKeyToUserPIN()V {
			.stack 8;
			.locals 3;

				L0:	getfield_a_this 48;		// reference ParkCard/PinManager.cryptoManager
					ifnull L2;
				L1:	getfield_a_this 49;		// reference ParkCard/PinManager.cardModel
					ifnonnull L3;
				L2:	return;
				L3:	getfield_a_this 48;		// reference ParkCard/PinManager.cryptoManager
					invokevirtual 160;		// ParkCard/CryptoManager.isKeyReady()Z
					ifne L5;
				L4:	return;
				L5:	getfield_a_this 49;		// reference ParkCard/PinManager.cardModel
					invokevirtual 181;		// ParkCard/CardModel.isMasterKeyWrapped()Z
					ifeq L7;
				L6:	return;
				L7:	getfield_b_this 46;		// boolean ParkCard/PinManager.pinCreated
					ifne L9;
				L8:	return;
				L9:	sconst_4;
					newarray 11;
					dup;
					sconst_0;
					bspush 49;
					bastore;
					dup;
					sconst_1;
					bspush 50;
					bastore;
					dup;
					sconst_2;
					bspush 51;
					bastore;
					dup;
					sconst_3;
					bspush 52;
					bastore;
					astore_1;
				L10:	getfield_a_this 49;		// reference ParkCard/PinManager.cardModel
					invokevirtual 139;		// ParkCard/CardModel.getSalt()[B
					astore_2;
				L11:	aload_2;
					ifnonnull L13;
				L12:	return;
				L13:	getfield_a_this 48;		// reference ParkCard/PinManager.cryptoManager
					aload_1;
					sconst_0;
					sconst_4;
					aload_2;
					sconst_0;
					bspush 16;
					sconst_1;
					invokevirtual 68;		// ParkCard/CryptoManager.deriveKeyFromPIN([BSB[BSSZ)V
					getfield_a_this 49;		// reference ParkCard/PinManager.cardModel
					invokevirtual 138;		// ParkCard/CardModel.getIV()[B
					astore_3;
				L14:	aload_3;
					ifnonnull L16;
				L15:	return;
				L16:	getfield_a_this 48;		// reference ParkCard/PinManager.cryptoManager
					getfield_a_this 49;		// reference ParkCard/PinManager.cardModel
					invokevirtual 182;		// ParkCard/CardModel.getWrappedMasterKey()[B
					sconst_0;
					aload_3;
					sconst_0;
					invokevirtual 161;		// ParkCard/CryptoManager.wrapLoadedMasterKey([BS[BS)V
					getfield_a_this 49;		// reference ParkCard/PinManager.cardModel
					sconst_1;
					invokevirtual 187;		// ParkCard/CardModel.setMasterKeyWrapped(Z)V
					return;
		}

	}

}
